{
  "profile": "tabular-data-package",
  "resources": [
    {
      "name": "servidores-2012-06",
      "path": "data/servidores-2012-06.csv.gz",
      "profile": "tabular-data-resource",
      "schema": "schema.json",
      "title": "Remuneração de Junho de 2012",
      "mediatype": "text/csv",
      "encoding": "windows-1252",
      "description": "Contém dados dos componentes da remuneração mensal dos servidores do poder Executivo do Estado de Minas Gerais",
      "dialect": "dialect.json",
      "format": "csv",
      "id": "ba880c9e-c154-4b77-8cad-4403aa6575af",
      "hash": "sha256:7c6c6f5e79028920b3dc1dc21dc619102f86e41ed61636c698858129baa68fc9"
    },
    {
      "name": "servidores-2012-07",
      "path": "data/servidores-2012-07.csv.gz",
      "profile": "tabular-data-resource",
      "schema": "schema.json",
      "title": "Remuneração de Julho de 2012",
      "mediatype": "text/csv",
      "encoding": "windows-1252",
      "description": "Contém dados dos componentes da remuneração mensal dos servidores do poder Executivo do Estado de Minas Gerais",
      "dialect": "dialect.json",
      "format": "csv",
      "id": "c8d68f68-9f7f-4cf1-824d-8d37b1313d3c",
      "hash": "sha256:dc1ad67ac4494a9d8f3c77b1a85ff905c3113be6d570409165f501a8eaf0483a"
    },
    {
      "name": "servidores-2012-08",
      "path": "data/servidores-2012-08.csv.gz",
      "profile": "tabular-data-resource",
      "schema": "schema.json",
      "title": "Remuneração de Agosto de 2012",
      "mediatype": "text/csv",
      "encoding": "windows-1252",
      "description": "Contém dados dos componentes da remuneração mensal dos servidores do poder Executivo do Estado de Minas Gerais",
      "dialect": "dialect.json",
      "format": "csv",
      "id": "6af9b432-c2bb-4e66-ad07-435d3d9cbb9d",
      "hash": "sha256:adc09530b869b7f38b2afddbd5185b74f0d2189f4346cf8a579aa1ccb25b6116"
    },
    {
      "name": "servidores-2012-09",
      "path": "data/servidores-2012-09.csv.gz",
      "profile": "tabular-data-resource",
      "schema": "schema.json",
      "title": "Remuneração de Setembro de 2012",
      "mediatype": "text/csv",
      "encoding": "windows-1252",
      "description": "Contém dados dos componentes da remuneração mensal dos servidores do poder Executivo do Estado de Minas Gerais",
      "dialect": "dialect.json",
      "format": "csv",
      "id": "f2e20b41-ca5d-4760-9072-1223e25d97e0",
      "hash": "sha256:5424ae530d6eccb1c4b250f6949944c86a10db16f60d3f6ead23534976ae2100"
    },
    {
      "name": "servidores-2012-10",
      "path": "data/servidores-2012-10.csv.gz",
      "profile": "tabular-data-resource",
      "schema": "schema.json",
      "title": "Remuneração de Outubro de 2012",
      "mediatype": "text/csv",
      "encoding": "windows-1252",
      "description": "Contém dados dos componentes da remuneração mensal dos servidores do poder Executivo do Estado de Minas Gerais",
      "dialect": "dialect.json",
      "format": "csv",
      "id": "53d263ac-8386-404b-b2c8-2a0649fa80ea",
      "hash": "sha256:eac5cb41a45bdedf9b3a729991719c9e9aa5229b30f47041330538e7877065cd"
    },
    {
      "name": "servidores-2012-11",
      "path": "data/servidores-2012-11.csv.gz",
      "profile": "tabular-data-resource",
      "schema": "schema.json",
      "title": "Remuneração de Novembro de 2012",
      "mediatype": "text/csv",
      "encoding": "windows-1252",
      "description": "Contém dados dos componentes da remuneração mensal dos servidores do poder Executivo do Estado de Minas Gerais",
      "dialect": "dialect.json",
      "format": "csv",
      "id": "0dad933f-5dde-4d1c-8587-2ddf0aadf1f6",
      "hash": "sha256:295e3a9fb44a79f9a888f00a75b43e8276f3de87464b39a3fe171667bea6ed8e"
    },
    {
      "name": "servidores-2012-12",
      "path": "data/servidores-2012-12.csv.gz",
      "profile": "tabular-data-resource",
      "schema": "schema.json",
      "title": "Remuneração de Dezembro de 2012",
      "mediatype": "text/csv",
      "encoding": "windows-1252",
      "description": "Contém dados dos componentes da remuneração mensal dos servidores do poder Executivo do Estado de Minas Gerais",
      "dialect": "dialect.json",
      "format": "csv",
      "id": "11c7a7a0-c50f-4a2d-b309-1547e94e6fe8",
      "hash": "sha256:048e6aadc20bf17f8d64328554ac6588527823d0ee1fc3730a964dc64134a8f4"
    },
    {
      "name": "servidores-2013-01",
      "path": "data/servidores-2013-01.csv.gz",
      "profile": "tabular-data-resource",
      "schema": "schema.json",
      "title": "Remuneração de Janeiro de 2013",
      "mediatype": "text/csv",
      "encoding": "windows-1252",
      "description": "Contém dados dos componentes da remuneração mensal dos servidores do poder Executivo do Estado de Minas Gerais",
      "dialect": "dialect.json",
      "format": "csv",
      "id": "f68cb3af-60f9-438b-8dcd-c10857ed0d1e",
      "hash": "sha256:048e6aadc20bf17f8d64328554ac6588527823d0ee1fc3730a964dc64134a8f4"
    },
    {
      "name": "servidores-2013-02",
      "path": "data/servidores-2013-02.csv.gz",
      "profile": "tabular-data-resource",
      "schema": "schema.json",
      "title": "Remuneração de Fevereiro de 2013",
      "mediatype": "text/csv",
      "encoding": "windows-1252",
      "description": "Contém dados dos componentes da remuneração mensal dos servidores do poder Executivo do Estado de Minas Gerais",
      "dialect": "dialect.json",
      "format": "csv",
      "id": "a249c555-1b5d-42a8-8186-956c9e881f1a",
      "hash": "sha256:a97438206109a494a180a50142143d0cc947368a9d178dd1e9dda8ae67d6ee8f"
    },
    {
      "name": "servidores-2013-03",
      "path": "data/servidores-2013-03.csv.gz",
      "profile": "tabular-data-resource",
      "schema": "schema.json",
      "title": "Remuneração de Março de 2013",
      "mediatype": "text/csv",
      "encoding": "windows-1252",
      "description": "Contém dados dos componentes da remuneração mensal dos servidores do poder Executivo do Estado de Minas Gerais",
      "dialect": "dialect.json",
      "format": "csv",
      "id": "159160cd-5b55-43e1-9e0e-71dc5ba650d9",
      "hash": "sha256:75a0b9e4d0ae7581b7d89b10ad2e1685a07a952e764b96a6bba825785a6a251a"
    },
    {
      "name": "servidores-2013-04",
      "path": "data/servidores-2013-04.csv.gz",
      "profile": "tabular-data-resource",
      "schema": "schema.json",
      "title": "Remuneração de Abril de 2013",
      "mediatype": "text/csv",
      "encoding": "windows-1252",
      "description": "Contém dados dos componentes da remuneração mensal dos servidores do poder Executivo do Estado de Minas Gerais",
      "dialect": "dialect.json",
      "format": "csv",
      "id": "534c1454-b426-4220-879b-2d7cce63ce00",
      "hash": "sha256:d939775a6c33b9b5b84ba7951d175481e5d4d91aee360f7636c98ebb136e140e"
    },
    {
      "name": "servidores-2013-05",
      "path": "data/servidores-2013-05.csv.gz",
      "profile": "tabular-data-resource",
      "schema": "schema.json",
      "title": "Remuneração de Maio de 2013",
      "mediatype": "text/csv",
      "encoding": "windows-1252",
      "description": "Contém dados dos componentes da remuneração mensal dos servidores do poder Executivo do Estado de Minas Gerais",
      "dialect": "dialect.json",
      "format": "csv",
      "id": "a51a7b5c-a45c-4ada-b15a-5fb0216bbe7b",
      "hash": "sha256:5294798aa5aabbe1989a693f0b807e231eabf2a7511fcb1a73183df395c928d0"
    },
    {
      "name": "servidores-2013-06",
      "path": "data/servidores-2013-06.csv.gz",
      "profile": "tabular-data-resource",
      "schema": "schema.json",
      "title": "Remuneração de Junho de 2013",
      "mediatype": "text/csv",
      "encoding": "windows-1252",
      "description": "Contém dados dos componentes da remuneração mensal dos servidores do poder Executivo do Estado de Minas Gerais",
      "dialect": "dialect.json",
      "format": "csv",
      "id": "15edf706-15af-4899-8e17-44d7823cb3a5",
      "hash": "sha256:fb01ca86c285324125c59b3f6ce56080d292117e7c36fe2021373b44df8cdf01"
    },
    {
      "name": "servidores-2013-07",
      "path": "data/servidores-2013-07.csv.gz",
      "profile": "tabular-data-resource",
      "schema": "schema.json",
      "title": "Remuneração de Julho de 2013",
      "mediatype": "text/csv",
      "encoding": "windows-1252",
      "description": "Contém dados dos componentes da remuneração mensal dos servidores do poder Executivo do Estado de Minas Gerais",
      "dialect": "dialect.json",
      "format": "csv",
      "id": "e4127929-c2e0-4be4-bf84-16db35298ddc",
      "hash": "sha256:71ef85b320d9e35ccc9b02e4a053f329f441277544533bceaef69ff0760ceaa0"
    },
    {
      "name": "servidores-2013-08",
      "path": "data/servidores-2013-08.csv.gz",
      "profile": "tabular-data-resource",
      "schema": "schema.json",
      "title": "Remuneração de Agosto de 2013",
      "mediatype": "text/csv",
      "encoding": "windows-1252",
      "description": "Contém dados dos componentes da remuneração mensal dos servidores do poder Executivo do Estado de Minas Gerais",
      "dialect": "dialect.json",
      "format": "csv",
      "id": "f68751d4-f929-4127-b510-6b2aedf157c5",
      "hash": "sha256:2e048c4c6746a63f0606a15832825362c58aabe6f141acfc93b15080d830831e"
    },
    {
      "name": "servidores-2013-09",
      "path": "data/servidores-2013-09.csv.gz",
      "profile": "tabular-data-resource",
      "schema": "schema.json",
      "title": "Remuneração de Setembro de 2013",
      "mediatype": "text/csv",
      "encoding": "windows-1252",
      "description": "Contém dados dos componentes da remuneração mensal dos servidores do poder Executivo do Estado de Minas Gerais",
      "dialect": "dialect.json",
      "format": "csv",
      "id": "13c8c380-cae9-4974-b8f0-8b4e48974f15",
      "hash": "sha256:b9ba6dd3a213d760154bb25600db61dfedae8b7747610bce5667c50cfb1fb34c"
    },
    {
      "name": "servidores-2013-10",
      "path": "data/servidores-2013-10.csv.gz",
      "profile": "tabular-data-resource",
      "schema": "schema.json",
      "title": "Remuneração de Outubro de 2013",
      "mediatype": "text/csv",
      "encoding": "windows-1252",
      "description": "Contém dados dos componentes da remuneração mensal dos servidores do poder Executivo do Estado de Minas Gerais",
      "dialect": "dialect.json",
      "format": "csv",
      "id": "65a110b5-7638-4c3c-b56b-e88bc01fe670",
      "hash": "sha256:69df5ef6871ccbb574c13a2c109e455c5b60b3d8c9ab45bfc601465f1b298c22"
    },
    {
      "name": "servidores-2013-11",
      "path": "data/servidores-2013-11.csv.gz",
      "profile": "tabular-data-resource",
      "schema": "schema.json",
      "title": "Remuneração de Novembro de 2013",
      "mediatype": "text/csv",
      "encoding": "windows-1252",
      "description": "Contém dados dos componentes da remuneração mensal dos servidores do poder Executivo do Estado de Minas Gerais",
      "dialect": "dialect.json",
      "format": "csv",
      "id": "407957cb-3030-48dc-9a6c-cdb602a4ebf4",
      "hash": "sha256:36fbda0a2db8311be26394f52a4b631e6b0f9d576179a4ecb2d444b7865fb30b"
    },
    {
      "name": "servidores-2013-12",
      "path": "data/servidores-2013-12.csv.gz",
      "profile": "tabular-data-resource",
      "schema": "schema.json",
      "title": "Remuneração de Dezembro de 2013",
      "mediatype": "text/csv",
      "encoding": "windows-1252",
      "description": "Contém dados dos componentes da remuneração mensal dos servidores do poder Executivo do Estado de Minas Gerais",
      "dialect": "dialect.json",
      "format": "csv",
      "id": "8a7318ae-79d2-4271-8921-300a452cab5e",
      "hash": "sha256:c2744f756813e6547ce588d4a7395f0519dd80b29c79c45557ca91502b975e61"
    },
    {
      "name": "servidores-2014-01",
      "path": "data/servidores-2014-01.csv.gz",
      "profile": "tabular-data-resource",
      "schema": "schema.json",
      "title": "Remuneração de Janeiro de 2014",
      "mediatype": "text/csv",
      "encoding": "windows-1252",
      "description": "Contém dados dos componentes da remuneração mensal dos servidores do poder Executivo do Estado de Minas Gerais",
      "dialect": "dialect.json",
      "format": "csv",
      "id": "82b47a61-97bb-49e4-a909-dbec1d50c05b",
      "hash": "sha256:b6f28c4d6c5684b32cb4873ab6bb282b246181fefb3fc7ce1b7c8ab450d9923d"
    },
    {
      "name": "servidores-2014-02",
      "path": "data/servidores-2014-02.csv.gz",
      "profile": "tabular-data-resource",
      "schema": "schema.json",
      "title": "Remuneração de Fevereiro de 2014",
      "mediatype": "text/csv",
      "encoding": "windows-1252",
      "description": "Contém dados dos componentes da remuneração mensal dos servidores do poder Executivo do Estado de Minas Gerais",
      "dialect": "dialect.json",
      "format": "csv",
      "id": "6bcb2def-57fb-4fb7-b073-0b225e4ab937",
      "hash": "sha256:ccbb64a2888e0845e55920b1efe318aab874c33bfcbb85c4929a96ec431e9ee2"
    },
    {
      "name": "servidores-2014-03",
      "path": "data/servidores-2014-03.csv.gz",
      "profile": "tabular-data-resource",
      "schema": "schema.json",
      "title": "Remuneração de Março de 2014",
      "mediatype": "text/csv",
      "encoding": "windows-1252",
      "description": "Contém dados dos componentes da remuneração mensal dos servidores do poder Executivo do Estado de Minas Gerais",
      "dialect": "dialect.json",
      "format": "csv",
      "id": "9ee34cc0-9286-4686-9b24-5d5df649ada3",
      "hash": "sha256:43fc6819b48956005d79fbc98a1fb2289e16c163021fe78e22ede587cca7292f"
    },
    {
      "name": "servidores-2014-04",
      "path": "data/servidores-2014-04.csv.gz",
      "profile": "tabular-data-resource",
      "schema": "schema.json",
      "title": "Remuneração de Abril de 2014",
      "mediatype": "text/csv",
      "encoding": "windows-1252",
      "description": "Contém dados dos componentes da remuneração mensal dos servidores do poder Executivo do Estado de Minas Gerais",
      "dialect": "dialect.json",
      "format": "csv",
      "id": "1e44510d-80b9-4110-87ed-d71e774ac14d",
      "hash": "sha256:fdd1afdb2888d22c92258f910f7ef29a45fa41a2486c636d1545e6db18811c8d"
    },
    {
      "name": "servidores-2014-05",
      "path": "data/servidores-2014-05.csv.gz",
      "profile": "tabular-data-resource",
      "schema": "schema.json",
      "title": "Remuneração de Maio de 2014",
      "mediatype": "text/csv",
      "encoding": "windows-1252",
      "description": "Contém dados dos componentes da remuneração mensal dos servidores do poder Executivo do Estado de Minas Gerais",
      "dialect": "dialect.json",
      "format": "csv",
      "id": "a391a3a6-fba6-4d21-bbb6-74fe6cfda964",
      "hash": "sha256:7bfb83254157e7c21dd192be22cb731e26e0471c1d59caa434ccfe9d3efe69a2"
    },
    {
      "name": "servidores-2014-06",
      "path": "data/servidores-2014-06.csv.gz",
      "profile": "tabular-data-resource",
      "schema": "schema.json",
      "title": "Remuneração de Junho de 2014",
      "mediatype": "text/csv",
      "encoding": "windows-1252",
      "description": "Contém dados dos componentes da remuneração mensal dos servidores do poder Executivo do Estado de Minas Gerais",
      "dialect": "dialect.json",
      "format": "csv",
      "id": "b3b61ab7-54b1-4be8-8892-889314f263a9",
      "hash": "sha256:884c8b0c40c6817527ce15fca3cd7778303b76251bfab0fa436af0e23dfae705"
    },
    {
      "name": "servidores-2014-07",
      "path": "data/servidores-2014-07.csv.gz",
      "profile": "tabular-data-resource",
      "schema": "schema.json",
      "title": "Remuneração de Julho de 2014",
      "mediatype": "text/csv",
      "encoding": "windows-1252",
      "description": "Contém dados dos componentes da remuneração mensal dos servidores do poder Executivo do Estado de Minas Gerais",
      "dialect": "dialect.json",
      "format": "csv",
      "id": "1656d127-0ae2-40dd-887d-96b5cd4c040e",
      "hash": "sha256:995785a3e0734d69775bde6c6f5bdeba6093db3c758d9de3f97e8fe4865cdaaf"
    },
    {
      "name": "servidores-2014-08",
      "path": "data/servidores-2014-08.csv.gz",
      "profile": "tabular-data-resource",
      "schema": "schema.json",
      "title": "Remuneração de Agosto de 2014",
      "mediatype": "text/csv",
      "encoding": "windows-1252",
      "description": "Contém dados dos componentes da remuneração mensal dos servidores do poder Executivo do Estado de Minas Gerais",
      "dialect": "dialect.json",
      "format": "csv",
      "id": "ed07ad9b-676a-47f8-aa6a-5c9a4325b05e",
      "hash": "sha256:fbf49a9317f3829e92c4b4069f81c59be674721634033c4502d782630f55f309"
    },
    {
      "name": "servidores-2014-09",
      "path": "data/servidores-2014-09.csv.gz",
      "profile": "tabular-data-resource",
      "schema": "schema.json",
      "title": "Remuneração de Setembro de 2014",
      "mediatype": "text/csv",
      "encoding": "windows-1252",
      "description": "Contém dados dos componentes da remuneração mensal dos servidores do poder Executivo do Estado de Minas Gerais",
      "dialect": "dialect.json",
      "format": "csv",
      "id": "7e5ecbad-2162-43c0-b346-45473e54a10d",
      "hash": "sha256:0d301fb41ab9f381d140859fb9057050e754b96568a2a675955fc60673d7352f"
    },
    {
      "name": "servidores-2014-10",
      "path": "data/servidores-2014-10.csv.gz",
      "profile": "tabular-data-resource",
      "schema": "schema.json",
      "title": "Remuneração de Outubro de 2014",
      "mediatype": "text/csv",
      "encoding": "windows-1252",
      "description": "Contém dados dos componentes da remuneração mensal dos servidores do poder Executivo do Estado de Minas Gerais",
      "dialect": "dialect.json",
      "format": "csv",
      "id": "5bca9f9b-b672-456c-a9c9-bbf9490bc1ce",
      "hash": "sha256:92f3d44334d59d44fb4f56853a0d16db7f0363a0e8bb48deacacb8fe908fb762"
    },
    {
      "name": "servidores-2014-11",
      "path": "data/servidores-2014-11.csv.gz",
      "profile": "tabular-data-resource",
      "schema": "schema.json",
      "title": "Remuneração de Novembro de 2014",
      "mediatype": "text/csv",
      "encoding": "windows-1252",
      "description": "Contém dados dos componentes da remuneração mensal dos servidores do poder Executivo do Estado de Minas Gerais",
      "dialect": "dialect.json",
      "format": "csv",
      "id": "428ce51d-004a-486d-9e40-40327360f14b",
      "hash": "sha256:5f2b593683c58b9174e53ed07438cb5940b9e9dd6d1b4ccd6b0ca599026e2e9e"
    },
    {
      "name": "servidores-2014-12",
      "path": "data/servidores-2014-12.csv.gz",
      "profile": "tabular-data-resource",
      "schema": "schema.json",
      "title": "Remuneração de Dezembro de 2014",
      "mediatype": "text/csv",
      "encoding": "windows-1252",
      "description": "Contém dados dos componentes da remuneração mensal dos servidores do poder Executivo do Estado de Minas Gerais",
      "dialect": "dialect.json",
      "format": "csv",
      "id": "afedff4f-6b01-4358-9611-7cc66191de9c",
      "hash": "sha256:f9ab7362204754004f12cc93f8cff38d79cc058732770361910016c26ca724c4"
    },
    {
      "name": "servidores-2015-01",
      "path": "data/servidores-2015-01.csv.gz",
      "profile": "tabular-data-resource",
      "schema": "schema.json",
      "title": "Remuneração de Janeiro de 2015",
      "mediatype": "text/csv",
      "encoding": "windows-1252",
      "description": "Contém dados dos componentes da remuneração mensal dos servidores do poder Executivo do Estado de Minas Gerais",
      "dialect": "dialect.json",
      "format": "csv",
      "id": "60b4abc2-9b57-4f78-b821-0f77cd988f9f",
      "hash": "sha256:edb6447305f42e0193d24419765e462bcd9492a34f5aa3cfc83f79c6f4aee976"
    },
    {
      "name": "servidores-2015-02",
      "path": "data/servidores-2015-02.csv.gz",
      "profile": "tabular-data-resource",
      "schema": "schema.json",
      "title": "Remuneração de Fevereiro de 2015",
      "mediatype": "text/csv",
      "encoding": "windows-1252",
      "description": "Contém dados dos componentes da remuneração mensal dos servidores do poder Executivo do Estado de Minas Gerais",
      "dialect": "dialect.json",
      "format": "csv",
      "id": "741a8b00-34de-424a-8826-fcfa66adca11",
      "hash": "sha256:047647d920ad48707170ce1bc50f8b3b5ce8252fb27024cfcdfcaa11f25558b7"
    },
    {
      "name": "servidores-2015-03",
      "path": "data/servidores-2015-03.csv.gz",
      "profile": "tabular-data-resource",
      "schema": "schema.json",
      "title": "Remuneração de Março de 2015",
      "mediatype": "text/csv",
      "encoding": "windows-1252",
      "description": "Contém dados dos componentes da remuneração mensal dos servidores do poder Executivo do Estado de Minas Gerais",
      "dialect": "dialect.json",
      "format": "csv",
      "id": "c563389d-af73-4faf-bbd6-b2224be4c494",
      "hash": "sha256:947b77eac204d9d651690bafac07adea0e1c93f6be1130a079565412084e7742"
    },
    {
      "name": "servidores-2015-04",
      "path": "data/servidores-2015-04.csv.gz",
      "profile": "tabular-data-resource",
      "schema": "schema.json",
      "title": "Remuneração de Abril de 2015",
      "mediatype": "text/csv",
      "encoding": "windows-1252",
      "description": "Contém dados dos componentes da remuneração mensal dos servidores do poder Executivo do Estado de Minas Gerais",
      "dialect": "dialect.json",
      "format": "csv",
      "id": "a5e1949a-7bfa-4702-8f0a-d433a21c7653",
      "hash": "sha256:dcebb094373a5eca419674c01dc4394f66c1412c6ef18c1df81bd3822768dc50"
    },
    {
      "name": "servidores-2015-05",
      "path": "data/servidores-2015-05.csv.gz",
      "profile": "tabular-data-resource",
      "schema": "schema.json",
      "title": "Remuneração de Maio de 2015",
      "mediatype": "text/csv",
      "encoding": "windows-1252",
      "description": "Contém dados dos componentes da remuneração mensal dos servidores do poder Executivo do Estado de Minas Gerais",
      "dialect": "dialect.json",
      "format": "csv",
      "id": "f5ec2b31-7cb7-40e6-8033-e843630f9baa",
      "hash": "sha256:a98ae6460e19d7f712ce6975de5bfc9a8e29df4dc599b8cd22d4c3ea6d4579fa"
    },
    {
      "name": "servidores-2015-06",
      "path": "data/servidores-2015-06.csv.gz",
      "profile": "tabular-data-resource",
      "schema": "schema.json",
      "title": "Remuneração de Junho de 2015",
      "mediatype": "text/csv",
      "encoding": "windows-1252",
      "description": "Contém dados dos componentes da remuneração mensal dos servidores do poder Executivo do Estado de Minas Gerais",
      "dialect": "dialect.json",
      "format": "csv",
      "id": "45a2e90f-9e89-4c94-88a5-c96484de02b3",
      "hash": "sha256:851884a5a1f27adb00a2f081c23e9af04d6484a90ef7e18cecf4a14800d33c65"
    },
    {
      "name": "servidores-2015-07",
      "path": "data/servidores-2015-07.csv.gz",
      "profile": "tabular-data-resource",
      "schema": "schema.json",
      "title": "Remuneração de Julho de 2015",
      "mediatype": "text/csv",
      "encoding": "windows-1252",
      "description": "Contém dados dos componentes da remuneração mensal dos servidores do poder Executivo do Estado de Minas Gerais",
      "dialect": "dialect.json",
      "format": "csv",
      "id": "93e44b31-198d-450f-a8d1-7e979d6b67be",
      "hash": "sha256:3fbf5b94003cd13c18e031a8c5961fd7c181b405b5f02a6b53ae08691f19bbbb"
    },
    {
      "name": "servidores-2015-08",
      "path": "data/servidores-2015-08.csv.gz",
      "profile": "tabular-data-resource",
      "schema": "schema.json",
      "title": "Remuneração de Agosto de 2015",
      "mediatype": "text/csv",
      "encoding": "windows-1252",
      "description": "Contém dados dos componentes da remuneração mensal dos servidores do poder Executivo do Estado de Minas Gerais",
      "dialect": "dialect.json",
      "format": "csv",
      "id": "7fa9b0d6-7f4b-40e1-8c91-e36e1320ab78",
      "hash": "sha256:25ef480f36a223e8ead321e6c661360e87c51aa3c7948c5c0871f77065bbad56"
    },
    {
      "name": "servidores-2015-09",
      "path": "data/servidores-2015-09.csv.gz",
      "profile": "tabular-data-resource",
      "schema": "schema.json",
      "title": "Remuneração de Setembro de 2015",
      "mediatype": "text/csv",
      "encoding": "windows-1252",
      "description": "Contém dados dos componentes da remuneração mensal dos servidores do poder Executivo do Estado de Minas Gerais",
      "dialect": "dialect.json",
      "format": "csv",
      "id": "2e84a029-bdc3-42be-9b09-6f0ca7ce7590",
      "hash": "sha256:251bde1acaffe13b6d63c4af67745562cdb836c1d08766ea3ee1c3252e1da822"
    },
    {
      "name": "servidores-2015-10",
      "path": "data/servidores-2015-10.csv.gz",
      "profile": "tabular-data-resource",
      "schema": "schema.json",
      "title": "Remuneração de Outubro de 2015",
      "mediatype": "text/csv",
      "encoding": "windows-1252",
      "description": "Contém dados dos componentes da remuneração mensal dos servidores do poder Executivo do Estado de Minas Gerais",
      "dialect": "dialect.json",
      "format": "csv",
      "id": "0e26bb24-6d98-46ad-a749-2b403ac15b6b",
      "hash": "sha256:b76ae2a5e91016bb0886b9c24c30863716e3be6a082cd50356dc2ea455eaf594"
    },
    {
      "name": "servidores-2015-11",
      "path": "data/servidores-2015-11.csv.gz",
      "profile": "tabular-data-resource",
      "schema": "schema.json",
      "title": "Remuneração de Novembro de 2015",
      "mediatype": "text/csv",
      "encoding": "windows-1252",
      "description": "Contém dados dos componentes da remuneração mensal dos servidores do poder Executivo do Estado de Minas Gerais",
      "dialect": "dialect.json",
      "format": "csv",
      "id": "a5bcd683-617d-4177-aa63-dd9d29ea2206",
      "hash": "sha256:f15d7a51c6c3584158754157ec141dabe0a643c398737d5487426d0205faa115"
    },
    {
      "name": "servidores-2015-12",
      "path": "data/servidores-2015-12.csv.gz",
      "profile": "tabular-data-resource",
      "schema": "schema.json",
      "title": "Remuneração de Dezembro de 2015",
      "mediatype": "text/csv",
      "encoding": "windows-1252",
      "description": "Contém dados dos componentes da remuneração mensal dos servidores do poder Executivo do Estado de Minas Gerais",
      "dialect": "dialect.json",
      "format": "csv",
      "id": "614f5ef8-4564-4dad-9977-84be80fdaf59",
      "hash": "sha256:1560261d38c8bac8fd78b4c0d8fa1acefab5c74fbd28a7ea13f737611bca780a"
    },
    {
      "name": "servidores-2016-01",
      "path": "data/servidores-2016-01.csv.gz",
      "profile": "tabular-data-resource",
      "schema": "schema.json",
      "title": "Remuneração de Janeiro de 2016",
      "mediatype": "text/csv",
      "encoding": "windows-1252",
      "description": "Contém dados dos componentes da remuneração mensal dos servidores do poder Executivo do Estado de Minas Gerais",
      "dialect": "dialect.json",
      "format": "csv",
      "id": "cc0b6a2b-a60e-44a0-90a9-c17bdfa394bb",
      "hash": "sha256:036bbe58e1cd708b16acf319861de4fcf22bec5461afda3d375664b88f6dafec"
    },
    {
      "name": "servidores-2016-02",
      "path": "data/servidores-2016-02.csv.gz",
      "profile": "tabular-data-resource",
      "schema": "schema.json",
      "title": "Remuneração de Fevereiro de 2016",
      "mediatype": "text/csv",
      "encoding": "windows-1252",
      "description": "Contém dados dos componentes da remuneração mensal dos servidores do poder Executivo do Estado de Minas Gerais",
      "dialect": "dialect.json",
      "format": "csv",
      "id": "d208dff8-c36c-4648-aecb-783d011da87a",
      "hash": "sha256:3830517bd6e3f6b5a0ddfeeb6e7c6667de0850da248db6f35d98116acc57d30d"
    },
    {
      "name": "servidores-2016-03",
      "path": "data/servidores-2016-03.csv.gz",
      "profile": "tabular-data-resource",
      "schema": "schema.json",
      "title": "Remuneração de Março de 2016",
      "mediatype": "text/csv",
      "encoding": "windows-1252",
      "description": "Contém dados dos componentes da remuneração mensal dos servidores do poder Executivo do Estado de Minas Gerais",
      "dialect": "dialect.json",
      "format": "csv",
      "id": "3d9193ce-6084-469b-ab3b-dd73e4bb3e5d",
      "hash": "sha256:51cab759e71a7d5b4c807ded37d6eb2b3c4b5b1fce268ea005b4ff0321d7960d"
    },
    {
      "name": "servidores-2016-04",
      "path": "data/servidores-2016-04.csv.gz",
      "profile": "tabular-data-resource",
      "schema": "schema.json",
      "title": "Remuneração de Abril de 2016",
      "mediatype": "text/csv",
      "encoding": "windows-1252",
      "description": "Contém dados dos componentes da remuneração mensal dos servidores do poder Executivo do Estado de Minas Gerais",
      "dialect": "dialect.json",
      "format": "csv",
      "id": "0da81537-2a9b-4445-abbe-0790ef35c022",
      "hash": "sha256:6818c60b48d798c27304aec006b9c2cba1601d2589d86f7ab719654c4cc724dc"
    },
    {
      "name": "servidores-2016-05",
      "path": "data/servidores-2016-05.csv.gz",
      "profile": "tabular-data-resource",
      "schema": "schema.json",
      "title": "Remuneração de Maio de 2016",
      "mediatype": "text/csv",
      "encoding": "windows-1252",
      "description": "Contém dados dos componentes da remuneração mensal dos servidores do poder Executivo do Estado de Minas Gerais",
      "dialect": "dialect.json",
      "format": "csv",
      "id": "95e95dcc-c157-4782-925f-0caca91a4471",
      "hash": "sha256:06e592211a013efcc1f97f77182fd57e69bfa373a0c9228e1dfa7c206fcf5b38"
    },
    {
      "name": "servidores-2016-06",
      "path": "data/servidores-2016-06.csv.gz",
      "profile": "tabular-data-resource",
      "schema": "schema.json",
      "title": "Remuneração de Junho de 2016",
      "mediatype": "text/csv",
      "encoding": "windows-1252",
      "description": "Contém dados dos componentes da remuneração mensal dos servidores do poder Executivo do Estado de Minas Gerais",
      "dialect": "dialect.json",
      "format": "csv",
      "id": "e075f2ec-8c78-4222-9cc8-4dbb3e004efe",
      "hash": "sha256:4dbd3d3d9b0be649bee080e3a42aa8d731f4f32718cc8d80e868d55f326663b5"
    },
    {
      "name": "servidores-2016-07",
      "path": "data/servidores-2016-07.csv.gz",
      "profile": "tabular-data-resource",
      "schema": "schema.json",
      "title": "Remuneração de Julho de 2016",
      "mediatype": "text/csv",
      "encoding": "windows-1252",
      "description": "Contém dados dos componentes da remuneração mensal dos servidores do poder Executivo do Estado de Minas Gerais",
      "dialect": "dialect.json",
      "format": "csv",
      "id": "8b981edb-03dd-4535-9810-6a4dcf4aeaa3",
      "hash": "sha256:9c8b1be2a733dfc3b0be4bf616fafe796c401ef6170fc29ed760eb7476605887"
    },
    {
      "name": "servidores-2016-08",
      "path": "data/servidores-2016-08.csv.gz",
      "profile": "tabular-data-resource",
      "schema": "schema.json",
      "title": "Remuneração de Agosto de 2016",
      "mediatype": "text/csv",
      "encoding": "windows-1252",
      "description": "Contém dados dos componentes da remuneração mensal dos servidores do poder Executivo do Estado de Minas Gerais",
      "dialect": "dialect.json",
      "format": "csv",
      "id": "65b1f4a9-f642-40c6-8208-65eaa1dff75a",
      "hash": "sha256:f536daeb79241aeef5d675cde79bba653d5324c13dc4ebacd9b93807071a5a9e"
    },
    {
      "name": "servidores-2016-09",
      "path": "data/servidores-2016-09.csv.gz",
      "profile": "tabular-data-resource",
      "schema": "schema.json",
      "title": "Remuneração de Setembro de 2016",
      "mediatype": "text/csv",
      "encoding": "windows-1252",
      "description": "Contém dados dos componentes da remuneração mensal dos servidores do poder Executivo do Estado de Minas Gerais",
      "dialect": "dialect.json",
      "format": "csv",
      "id": "b2939148-38f5-4ed0-89ac-05525e2e3e6c",
      "hash": "sha256:f35d3e8cc0299ca0d2e5b2aadb59bc62348aa4e088b16edc734ce02fffb18305"
    },
    {
      "name": "servidores-2016-10",
      "path": "data/servidores-2016-10.csv.gz",
      "profile": "tabular-data-resource",
      "schema": "schema.json",
      "title": "Remuneração de Outubro de 2016",
      "mediatype": "text/csv",
      "encoding": "windows-1252",
      "description": "Contém dados dos componentes da remuneração mensal dos servidores do poder Executivo do Estado de Minas Gerais",
      "dialect": "dialect.json",
      "format": "csv",
      "id": "37a15058-2a9f-40ac-b993-58d3b0a63933",
      "hash": "sha256:75e71c649e6af4855c26f9ebd3415b342b82dbe6ac10da899a11b3477f8375db"
    },
    {
      "name": "servidores-2016-11",
      "path": "data/servidores-2016-11.csv.gz",
      "profile": "tabular-data-resource",
      "schema": "schema.json",
      "title": "Remuneração de Novembro de 2016",
      "mediatype": "text/csv",
      "encoding": "windows-1252",
      "description": "Contém dados dos componentes da remuneração mensal dos servidores do poder Executivo do Estado de Minas Gerais",
      "dialect": "dialect.json",
      "format": "csv",
      "id": "f28b09bf-53f7-406d-9848-bbd1d42ff788",
      "hash": "sha256:092e503b6a0bbbb6b7cb1f3d17d1c01a647e07ddbed8d38cde2fab3e4f382d84"
    },
    {
      "name": "servidores-2016-12",
      "path": "data/servidores-2016-12.csv.gz",
      "profile": "tabular-data-resource",
      "schema": "schema.json",
      "title": "Remuneração de Dezembro de 2016",
      "mediatype": "text/csv",
      "encoding": "windows-1252",
      "description": "Contém dados dos componentes da remuneração mensal dos servidores do poder Executivo do Estado de Minas Gerais",
      "dialect": "dialect.json",
      "format": "csv",
      "id": "7e057533-103a-4463-aed4-c3e0ecc6ea04",
      "hash": "sha256:30268a7005b1321d605d6154d06df9eb5838faf8edcd8d5c5cfa4d62486127bf"
    },
    {
      "name": "servidores-2017-01",
      "path": "data/servidores-2017-01.csv.gz",
      "profile": "tabular-data-resource",
      "schema": "schema.json",
      "title": "Remuneração de Janeiro de 2017",
      "mediatype": "text/csv",
      "encoding": "windows-1252",
      "description": "Contém dados dos componentes da remuneração mensal dos servidores do poder Executivo do Estado de Minas Gerais",
      "dialect": "dialect.json",
      "format": "csv",
      "id": "2c09dcc7-ecd7-49f9-875d-ef8425abca41",
      "hash": "sha256:b95b62faf8f0f2e611ecf2eee91e89ec260555fe8592dc2d87bd60ed37f1803f"
    },
    {
      "name": "servidores-2017-02",
      "path": "data/servidores-2017-02.csv.gz",
      "profile": "tabular-data-resource",
      "schema": "schema.json",
      "title": "Remuneração de Fevereiro de 2017",
      "mediatype": "text/csv",
      "encoding": "windows-1252",
      "description": "Contém dados dos componentes da remuneração mensal dos servidores do poder Executivo do Estado de Minas Gerais",
      "dialect": "dialect.json",
      "format": "csv",
      "id": "e1c8f361-2914-41e5-8651-3cf56459c3b5",
      "hash": "sha256:b95b62faf8f0f2e611ecf2eee91e89ec260555fe8592dc2d87bd60ed37f1803f"
    },
    {
      "name": "servidores-2017-03",
      "path": "data/servidores-2017-03.csv.gz",
      "profile": "tabular-data-resource",
      "schema": "schema.json",
      "title": "Remuneração de Março de 2017",
      "mediatype": "text/csv",
      "encoding": "windows-1252",
      "description": "Contém dados dos componentes da remuneração mensal dos servidores do poder Executivo do Estado de Minas Gerais",
      "dialect": "dialect.json",
      "format": "csv",
      "id": "bcc14261-9665-42d2-ba80-90eefe484cd6",
      "hash": "sha256:c8b65224b85f329087ffa9fd14fec5c285a46565b9b4b8dc7cdae08f37f39cbd"
    },
    {
      "name": "servidores-2017-04",
      "path": "data/servidores-2017-04.csv.gz",
      "profile": "tabular-data-resource",
      "schema": "schema.json",
      "title": "Remuneração de Abril de 2017",
      "mediatype": "text/csv",
      "encoding": "windows-1252",
      "description": "Contém dados dos componentes da remuneração mensal dos servidores do poder Executivo do Estado de Minas Gerais",
      "dialect": "dialect.json",
      "format": "csv",
      "id": "51c68be2-ec47-475d-b1f9-6ac36eeffdf0",
      "hash": "sha256:dad3218254c654745ac3478a08c1cc1144ba8ff87517794990a469bcfc0e69dc"
    },
    {
      "name": "servidores-2017-05",
      "path": "data/servidores-2017-05.csv.gz",
      "profile": "tabular-data-resource",
      "schema": "schema.json",
      "title": "Remuneração de Maio de 2017",
      "mediatype": "text/csv",
      "encoding": "windows-1252",
      "description": "Contém dados dos componentes da remuneração mensal dos servidores do poder Executivo do Estado de Minas Gerais",
      "dialect": "dialect.json",
      "format": "csv",
      "id": "72d0e485-1e6f-42bc-8a8d-a1a8102086a1",
      "hash": "sha256:10104500361afd85c45e5b686f4e91f0168f5bfa5aacba361cc139d998b259c9"
    },
    {
      "name": "servidores-2017-06",
      "path": "data/servidores-2017-06.csv.gz",
      "profile": "tabular-data-resource",
      "schema": "schema.json",
      "title": "Remuneração de Junho de 2017",
      "mediatype": "text/csv",
      "encoding": "windows-1252",
      "description": "Contém dados dos componentes da remuneração mensal dos servidores do poder Executivo do Estado de Minas Gerais",
      "dialect": "dialect.json",
      "format": "csv",
      "id": "cf245e32-a77a-4826-8da2-b2984272b8ac",
      "hash": "sha256:e7b8f5d1c873f21ad608909241c487577b1a9fbf6e7e3186f29a2f42165b6ee3"
    },
    {
      "name": "servidores-2017-07",
      "path": "data/servidores-2017-07.csv.gz",
      "profile": "tabular-data-resource",
      "schema": "schema.json",
      "title": "Remuneração de Julho de 2017",
      "mediatype": "text/csv",
      "encoding": "windows-1252",
      "description": "Contém dados dos componentes da remuneração mensal dos servidores do poder Executivo do Estado de Minas Gerais",
      "dialect": "dialect.json",
      "format": "csv",
      "id": "2cb0779f-170f-41dd-979d-8f2d3c7eb8b5",
      "hash": "sha256:d6f981bc7bbb1c0b4f13c12199bd0efe475208b7325a34167c7b5b1069ab0006"
    },
    {
      "name": "servidores-2017-08",
      "path": "data/servidores-2017-08.csv.gz",
      "profile": "tabular-data-resource",
      "schema": "schema.json",
      "title": "Remuneração de Agosto de 2017",
      "mediatype": "text/csv",
      "encoding": "windows-1252",
      "description": "Contém dados dos componentes da remuneração mensal dos servidores do poder Executivo do Estado de Minas Gerais",
      "dialect": "dialect.json",
      "format": "csv",
      "id": "955457c8-d9ac-4ce9-ae1f-e57732aa5b05",
      "hash": "sha256:19fd02995802c4055a0214f7f9a610de48c941b69254184e70cb5c4187111398"
    },
    {
      "name": "servidores-2017-09",
      "path": "data/servidores-2017-09.csv.gz",
      "profile": "tabular-data-resource",
      "schema": "schema.json",
      "title": "Remuneração de Setembro de 2017",
      "mediatype": "text/csv",
      "encoding": "windows-1252",
      "description": "Contém dados dos componentes da remuneração mensal dos servidores do poder Executivo do Estado de Minas Gerais",
      "dialect": "dialect.json",
      "format": "csv",
      "id": "e75aa3ff-428d-4dda-b1ec-cf783b857bc6",
      "hash": "sha256:64b87e6f0ef33da2d544c23954d0d6e3037fdb8de94c1d2a57aab4268e23ea67"
    },
    {
      "name": "servidores-2017-10",
      "path": "data/servidores-2017-10.csv.gz",
      "profile": "tabular-data-resource",
      "schema": "schema.json",
      "title": "Remuneração de Outubro de 2017",
      "mediatype": "text/csv",
      "encoding": "windows-1252",
      "description": "Contém dados dos componentes da remuneração mensal dos servidores do poder Executivo do Estado de Minas Gerais",
      "dialect": "dialect.json",
      "format": "csv",
      "id": "62a8cfc3-f62d-415c-89c5-f278fa897671",
      "hash": "sha256:7dcf48a52fd569b32f2f6b51499651458008bcc495ea9ed3a7d78c89dc31042f"
    },
    {
      "name": "servidores-2017-11",
      "path": "data/servidores-2017-11.csv.gz",
      "profile": "tabular-data-resource",
      "schema": "schema.json",
      "title": "Remuneração de Novembro de 2017",
      "mediatype": "text/csv",
      "encoding": "windows-1252",
      "description": "Contém dados dos componentes da remuneração mensal dos servidores do poder Executivo do Estado de Minas Gerais",
      "dialect": "dialect.json",
      "format": "csv",
      "id": "34148e81-1ff1-43d0-aaac-f9b30c332ffb",
      "hash": "sha256:4af3339320e0f1074f64cc7b2c8b2107bf6055dec5b2b006e29f8083e430bfdc"
    },
    {
      "name": "servidores-2017-12",
      "path": "data/servidores-2017-12.csv.gz",
      "profile": "tabular-data-resource",
      "schema": "schema.json",
      "title": "Remuneração de Dezembro de 2017",
      "mediatype": "text/csv",
      "encoding": "windows-1252",
      "description": "Contém dados dos componentes da remuneração mensal dos servidores do poder Executivo do Estado de Minas Gerais",
      "dialect": "dialect.json",
      "format": "csv",
      "id": "bfd8558d-006d-4c0e-8d96-260bc54f4701",
      "hash": "sha256:cc9bae030253574a5fd7da14a1b4130618f40277d53e0cac2f8bdf0fee1a7a45"
    },
    {
      "name": "servidores-2018-01",
      "path": "data/servidores-2018-01.csv.gz",
      "profile": "tabular-data-resource",
      "schema": "schema.json",
      "title": "Remuneração de Janeiro de 2018",
      "mediatype": "text/csv",
      "encoding": "windows-1252",
      "description": "Contém dados dos componentes da remuneração mensal dos servidores do poder Executivo do Estado de Minas Gerais",
      "dialect": "dialect.json",
      "format": "csv",
      "id": "b4b1acab-8524-41f8-9927-86363dd31670",
      "hash": "sha256:ac169a52b6ef9b9e9dd90d27b3a8712efc19a5c748916182f01522c3df397724"
    },
    {
      "name": "servidores-2018-02",
      "path": "data/servidores-2018-02.csv.gz",
      "profile": "tabular-data-resource",
      "schema": "schema.json",
      "title": "Remuneração de Fevereiro de 2018",
      "mediatype": "text/csv",
      "encoding": "windows-1252",
      "description": "Contém dados dos componentes da remuneração mensal dos servidores do poder Executivo do Estado de Minas Gerais",
      "dialect": "dialect.json",
      "format": "csv",
      "id": "a39451d7-f20b-40cf-ba3c-9e3f6f014c6e",
      "hash": "sha256:f9b25c0b829abbfed30d45ded8ad1d0836dec3b90add1d5775010dc10e6d7b34"
    },
    {
      "name": "servidores-2018-03",
      "path": "data/servidores-2018-03.csv.gz",
      "profile": "tabular-data-resource",
      "schema": "schema.json",
      "title": "Remuneração de Março de 2018",
      "mediatype": "text/csv",
      "encoding": "windows-1252",
      "description": "Contém dados dos componentes da remuneração mensal dos servidores do poder Executivo do Estado de Minas Gerais",
      "dialect": "dialect.json",
      "format": "csv",
      "id": "6585fcfe-bc4a-4d8c-84d8-765533a8658d",
      "hash": "sha256:90696f4ba92564002e93ec7911886b3202ea608041aeee274ca0fccb6a707c0c"
    },
    {
      "name": "servidores-2018-04",
      "path": "data/servidores-2018-04.csv.gz",
      "profile": "tabular-data-resource",
      "schema": "schema.json",
      "title": "Remuneração de Abril de 2018",
      "mediatype": "text/csv",
      "encoding": "windows-1252",
      "description": "Contém dados dos componentes da remuneração mensal dos servidores do poder Executivo do Estado de Minas Gerais",
      "dialect": "dialect.json",
      "format": "csv",
      "id": "4c9aadab-7865-4871-9483-ddad195ef70b",
      "hash": "sha256:804cadf0cec4611d76916b3006b21d178a696b7c1d55d539e48ae5b94365a0fe"
    },
    {
      "name": "servidores-2018-05",
      "path": "data/servidores-2018-05.csv.gz",
      "profile": "tabular-data-resource",
      "schema": "schema.json",
      "title": "Remuneração de Maio de 2018",
      "mediatype": "text/csv",
      "encoding": "windows-1252",
      "description": "Contém dados dos componentes da remuneração mensal dos servidores do poder Executivo do Estado de Minas Gerais",
      "dialect": "dialect.json",
      "format": "csv",
      "id": "916ca6e7-915d-4834-914a-791fe74830bc",
      "hash": "sha256:aaf6d021ed54959715a7ce18534a7654ce22e0c21c26e07a5e7b25cc80a8a890"
    },
    {
      "name": "servidores-2018-06",
      "path": "data/servidores-2018-06.csv.gz",
      "profile": "tabular-data-resource",
      "schema": "schema.json",
      "title": "Remuneração de Junho de 2018",
      "mediatype": "text/csv",
      "encoding": "windows-1252",
      "description": "Contém dados dos componentes da remuneração mensal dos servidores do poder Executivo do Estado de Minas Gerais",
      "dialect": "dialect.json",
      "format": "csv",
      "id": "e49e5f7c-c241-4258-a41c-ce3c80b9f21e",
      "hash": "sha256:c6de229ce061b941ec0ec42342162ae13f9b0a1126b861d2083ab6012b3a7155"
    },
    {
      "name": "servidores-2018-07",
      "path": "data/servidores-2018-07.csv.gz",
      "profile": "tabular-data-resource",
      "schema": "schema.json",
      "title": "Remuneração de Julho de 2018",
      "mediatype": "text/csv",
      "encoding": "windows-1252",
      "description": "Contém dados dos componentes da remuneração mensal dos servidores do poder Executivo do Estado de Minas Gerais",
      "dialect": "dialect.json",
      "format": "csv",
      "id": "90dffc42-0386-4968-a0a7-92671017610c",
      "hash": "sha256:2667bba4b38b87ea9e7df16f05e12686e08843b47a6b4962a90e1c3f140593e5"
    },
    {
      "name": "servidores-2018-08",
      "path": "data/servidores-2018-08.csv.gz",
      "profile": "tabular-data-resource",
      "schema": "schema.json",
      "title": "Remuneração de Agosto de 2018",
      "mediatype": "text/csv",
      "encoding": "windows-1252",
      "description": "Contém dados dos componentes da remuneração mensal dos servidores do poder Executivo do Estado de Minas Gerais",
      "dialect": "dialect.json",
      "format": "csv",
      "id": "1a052dc9-12f9-4d07-a5a7-5349d232bfb9",
      "hash": "sha256:b37399c782c5978b5a70740492bc04f90c48fd3b208b402cdbd62c1be308939f"
    },
    {
      "name": "servidores-2018-09",
      "path": "data/servidores-2018-09.csv.gz",
      "profile": "tabular-data-resource",
      "schema": "schema.json",
      "title": "Remuneração de Setembro de 2018",
      "mediatype": "text/csv",
      "encoding": "windows-1252",
      "description": "Contém dados dos componentes da remuneração mensal dos servidores do poder Executivo do Estado de Minas Gerais",
      "dialect": "dialect.json",
      "format": "csv",
      "id": "50533cf8-ff35-41c0-a397-89d3c919db71",
      "hash": "sha256:8c9a3a9f3e11d9a352a125ced4ee8bd968c1ad3fed405076998059badaf012d6"
    },
    {
      "name": "servidores-2018-10",
      "path": "data/servidores-2018-10.csv.gz",
      "profile": "tabular-data-resource",
      "schema": "schema.json",
      "title": "Remuneração de Outubro de 2018",
      "mediatype": "text/csv",
      "encoding": "windows-1252",
      "description": "Contém dados dos componentes da remuneração mensal dos servidores do poder Executivo do Estado de Minas Gerais",
      "dialect": "dialect.json",
      "format": "csv",
      "id": "aa323410-0a95-4f78-b18e-9ca4d8f243bd",
      "hash": "sha256:2284b27466841c800cc8189fcf449e6d313874cfaa689faa9e15606b2e25ffb9"
    },
    {
      "name": "servidores-2018-11",
      "path": "data/servidores-2018-11.csv.gz",
      "profile": "tabular-data-resource",
      "schema": "schema.json",
      "title": "Remuneração de Novembro de 2018",
      "mediatype": "text/csv",
      "encoding": "windows-1252",
      "description": "Contém dados dos componentes da remuneração mensal dos servidores do poder Executivo do Estado de Minas Gerais",
      "dialect": "dialect.json",
      "format": "csv",
      "id": "b3e3f6ae-2618-4296-9273-f8dbe0b080c7",
      "hash": "sha256:706684b4fe40697e3a39138568234ffc75279cef22760d9f18084c48303e8c0f"
    },
    {
      "name": "servidores-2018-12",
      "path": "data/servidores-2018-12.csv.gz",
      "profile": "tabular-data-resource",
      "schema": "schema.json",
      "title": "Remuneração de Dezembro de 2018",
      "mediatype": "text/csv",
      "encoding": "windows-1252",
      "description": "Contém dados dos componentes da remuneração mensal dos servidores do poder Executivo do Estado de Minas Gerais",
      "dialect": "dialect.json",
      "format": "csv",
      "id": "9da1eec0-852f-4a89-97ae-c7182a13c127",
      "hash": "sha256:05cea35390290df1757b02a590059e4359e8a65dd04c5f90f64afa2f5ae549d5"
    },
    {
      "name": "servidores-2019-01",
      "path": "data/servidores-2019-01.csv.gz",
      "profile": "tabular-data-resource",
      "schema": "schema.json",
      "title": "Remuneração de Janeiro de 2019",
      "mediatype": "text/csv",
      "encoding": "windows-1252",
      "description": "Contém dados dos componentes da remuneração mensal dos servidores do poder Executivo do Estado de Minas Gerais",
      "dialect": "dialect.json",
      "format": "csv",
      "id": "883f50df-ebda-48ce-a1bd-6ecfe97bdd64",
      "hash": "sha256:302a7c5e4682f8dd292497260a4995a367ed25d0f22312e4b7f8e60a2fd8af55"
    },
    {
      "name": "servidores-2019-02",
      "path": "data/servidores-2019-02.csv.gz",
      "profile": "tabular-data-resource",
      "schema": "schema.json",
      "title": "Remuneração de Fevereiro de 2019",
      "mediatype": "text/csv",
      "encoding": "windows-1252",
      "description": "Contém dados dos componentes da remuneração mensal dos servidores do poder Executivo do Estado de Minas Gerais",
      "dialect": "dialect.json",
      "format": "csv",
      "id": "9d7c077e-0dec-40d5-a6ea-712e369f702e",
      "hash": "sha256:b0bc34d64dcb09ad4996b3a38394fc69ed7791b499cb3ba1e917f4ff8bff78a6"
    },
    {
      "name": "servidores-2019-03",
      "path": "data/servidores-2019-03.csv.gz",
      "profile": "tabular-data-resource",
      "schema": "schema.json",
      "title": "Remuneração de Março de 2019",
      "mediatype": "text/csv",
      "encoding": "windows-1252",
      "description": "Contém dados dos componentes da remuneração mensal dos servidores do poder Executivo do Estado de Minas Gerais",
      "dialect": "dialect.json",
      "format": "csv",
      "id": "60c84d7a-75e6-47c4-8dd8-45be12020da2",
      "hash": "sha256:a7cef9d2115bbc2bb780a2004ef4d54e06c5ad5d53c36c62f6617a504a3d3269"
    },
    {
      "name": "servidores-2019-04",
      "path": "data/servidores-2019-04.csv.gz",
      "profile": "tabular-data-resource",
      "schema": "schema.json",
      "title": "Remuneração de Abril de 2019",
      "mediatype": "text/csv",
      "encoding": "windows-1252",
      "description": "Contém dados dos componentes da remuneração mensal dos servidores do poder Executivo do Estado de Minas Gerais",
      "dialect": "dialect.json",
      "format": "csv",
      "id": "c73d2c48-a2ec-48c4-9b1e-64c1477d36e4",
      "hash": "sha256:659b73e152601aa712f37963fca02fc05839b618ff02cec15d300212603dfbcf"
    },
    {
      "name": "servidores-2019-05",
      "path": "data/servidores-2019-05.csv.gz",
      "profile": "tabular-data-resource",
      "schema": "schema.json",
      "title": "Remuneração de Maio de 2019",
      "mediatype": "text/csv",
      "encoding": "windows-1252",
      "description": "Contém dados dos componentes da remuneração mensal dos servidores do poder Executivo do Estado de Minas Gerais",
      "dialect": "dialect.json",
      "format": "csv",
      "id": "bd5b4d50-e762-49b6-bb59-1e7d9ff2020f",
      "hash": "sha256:ea4648a678d67b0fed77d8f4b9e855828f40b2434727ad99c7a364174295f012"
    },
    {
      "name": "servidores-2019-06",
      "path": "data/servidores-2019-06.csv.gz",
      "profile": "tabular-data-resource",
      "schema": "schema.json",
      "title": "Remuneração de Junho de 2019",
      "mediatype": "text/csv",
      "encoding": "windows-1252",
      "description": "Contém dados dos componentes da remuneração mensal dos servidores do poder Executivo do Estado de Minas Gerais",
      "dialect": "dialect.json",
      "format": "csv",
      "id": "87dbece3-e5b0-4e6b-9a28-c35280d55e7b",
      "hash": "sha256:77f37452a05eaff644844e41131ba41318330ed7ff030b8358fc797279b849ac"
    },
    {
      "name": "servidores-2019-07",
      "path": "data/servidores-2019-07.csv.gz",
      "profile": "tabular-data-resource",
      "schema": "schema.json",
      "title": "Remuneração de Julho de 2019",
      "mediatype": "text/csv",
      "encoding": "windows-1252",
      "description": "Contém dados dos componentes da remuneração mensal dos servidores do poder Executivo do Estado de Minas Gerais",
      "dialect": "dialect.json",
      "format": "csv",
      "id": "2913baf3-1465-446d-b6a4-2678cadf0f11",
      "hash": "sha256:f0f1e7aa8a9c4faf055a0d6c672abe46817e5dbdc6e065dc1bd21f2049fe8545"
    },
    {
      "name": "servidores-2019-08",
      "path": "data/servidores-2019-08.csv.gz",
      "profile": "tabular-data-resource",
      "schema": "schema.json",
      "title": "Remuneração de Agosto de 2019",
      "mediatype": "text/csv",
      "encoding": "windows-1252",
      "description": "Contém dados dos componentes da remuneração mensal dos servidores do poder Executivo do Estado de Minas Gerais",
      "dialect": "dialect.json",
      "format": "csv",
      "id": "278d9c80-eb0e-4ea4-a6b1-304ca6619fab",
      "hash": "sha256:8ef17152c50169df427cd4e38ee6f430fa449077f58240035263c931c42152a0"
    },
    {
      "name": "servidores-2019-09",
      "path": "data/servidores-2019-09.csv.gz",
      "profile": "tabular-data-resource",
      "schema": "schema.json",
      "title": "Remuneração de Setembro de 2019",
      "mediatype": "text/csv",
      "encoding": "windows-1252",
      "description": "Contém dados dos componentes da remuneração mensal dos servidores do poder Executivo do Estado de Minas Gerais",
      "dialect": "dialect.json",
      "format": "csv",
      "id": "f0996d43-c132-42d8-b349-7a17ce6e2ded",
      "hash": "sha256:8c3436cfdbefa67a7985445664df8b96f9afb1dc484179f9dbe683a8782c9f40"
    },
    {
      "name": "servidores-2019-10",
      "path": "data/servidores-2019-10.csv.gz",
      "profile": "tabular-data-resource",
      "schema": "schema.json",
      "title": "Remuneração de Outubro de 2019",
      "mediatype": "text/csv",
      "encoding": "windows-1252",
      "description": "Contém dados dos componentes da remuneração mensal dos servidores do poder Executivo do Estado de Minas Gerais",
      "dialect": "dialect.json",
      "format": "csv",
      "id": "049262f8-4702-4550-bc77-608795333f0a",
      "hash": "sha256:9b31ea62bb5ea5aaca12bdfeddf0e77333f1414639b454e96524cc83dddd46e1"
    },
    {
      "name": "servidores-2019-11",
      "path": "data/servidores-2019-11.csv.gz",
      "profile": "tabular-data-resource",
      "schema": "schema.json",
      "title": "Remuneração de Novembro de 2019",
      "mediatype": "text/csv",
      "encoding": "windows-1252",
      "description": "Contém dados dos componentes da remuneração mensal dos servidores do poder Executivo do Estado de Minas Gerais",
      "dialect": "dialect.json",
      "format": "csv",
      "id": "79cb3d5d-4182-420c-bb22-bfc2e07a5e69",
      "hash": "sha256:abdf4374a8acb70e367d9374296e4e1c31efea4577e9fa5baae7fb41f981269f"
    },
    {
      "name": "servidores-2019-12",
      "path": "data/servidores-2019-12.csv.gz",
      "profile": "tabular-data-resource",
      "schema": "schema.json",
      "title": "Remuneração de Dezembro de 2019",
      "mediatype": "text/csv",
      "encoding": "windows-1252",
      "description": "Contém dados dos componentes da remuneração mensal dos servidores do poder Executivo do Estado de Minas Gerais",
      "dialect": "dialect.json",
      "format": "csv",
      "id": "f3684c58-3e64-4563-964d-8a2e0bfb6818",
      "hash": "sha256:4fb315bbb03c72d3b31816f1112d6fdb7d341b1a29efbf9747aa9fe1c1c73726"
    },
    {
      "name": "servidores-2020-01",
      "path": "data/servidores-2020-01.csv.gz",
      "profile": "tabular-data-resource",
      "schema": "schema.json",
      "title": "Remuneração de Janeiro de 2020",
      "mediatype": "text/csv",
      "encoding": "windows-1252",
      "description": "Contém dados dos componentes da remuneração mensal dos servidores do poder Executivo do Estado de Minas Gerais",
      "dialect": "dialect.json",
      "format": "csv",
      "id": "b76bd963-be41-4ad5-a6ea-d61da5d3297f",
      "hash": "sha256:a092aa50f652c9923b131ba575f90e22f1612d5b2e3ed4d81bd5129b65a83f09"
    },
    {
      "name": "servidores-2020-02",
      "path": "data/servidores-2020-02.csv.gz",
      "profile": "tabular-data-resource",
      "schema": "schema.json",
      "description": "Contém dados dos componentes da remuneração mensal dos servidores do poder Executivo do Estado de Minas Gerais",
      "title": "Remuneração de Fevereiro de 2020",
      "mediatype": "text/csv",
      "encoding": "windows-1252",
      "dialect": "dialect.json",
      "format": "csv",
      "id": "8658bfe1-055c-40b8-8892-8f00b68c74a3",
      "hash": "sha256:f66790d415df8480cab7950edbf3bc0a3ed3df9069350e094a05f47ecf1d58f1"
    },
    {
      "name": "servidores-2020-03",
      "path": "data/servidores-2020-03.csv.gz",
      "profile": "tabular-data-resource",
      "schema": "schema.json",
      "description": "Contém dados dos componentes da remuneração mensal dos servidores do poder Executivo do Estado de Minas Gerais",
      "title": "Remuneração de Março de 2020",
      "mediatype": "text/csv",
      "encoding": "windows-1252",
      "dialect": "dialect.json",
      "format": "csv",
      "id": "0676ce88-5c2e-412d-b545-33d5dff617df",
      "hash": "sha256:6fd041f12a4905f77fea1465805e097d97e0290202aefad2b8355a8b61b5e3d7"
    },
    {
      "name": "servidores-2020-04",
      "path": "data/servidores-2020-04.csv.gz",
      "profile": "tabular-data-resource",
      "schema": "schema.json",
      "description": "Contém dados dos componentes da remuneração mensal dos servidores do poder Executivo do Estado de Minas Gerais",
      "title": "Remuneração de Abril de 2020",
      "mediatype": "text/csv",
      "encoding": "windows-1252",
      "dialect": "dialect.json",
      "format": "csv",
      "id": "37b32c19-a944-4545-a7fb-a415512c1dc4",
      "hash": "sha256:dfc103869753fbb43cff2e18b5d53f138eb91dd504f0ff458e767330e602f9fd"
    },
    {
      "name": "servidores-2020-05",
      "path": "data/servidores-2020-05.csv.gz",
      "profile": "tabular-data-resource",
      "schema": "schema.json",
      "description": "Contém dados dos componentes da remuneração mensal dos servidores do poder Executivo do Estado de Minas Gerais",
      "title": "Remuneração de Maio de 2020",
      "mediatype": "text/csv",
      "encoding": "windows-1252",
      "dialect": "dialect.json",
      "format": "csv",
      "id": "cc42c116-c07c-4af6-8ff3-d59c60a63658",
      "hash": "sha256:c266ba548ba20cc4ab088a37f7ee8774932c5bc0b8fb99e0a17c6cf91c7a5044"
    },
    {
      "name": "servidores-2020-06",
      "path": "data/servidores-2020-06.csv.gz",
      "profile": "tabular-data-resource",
      "schema": "schema.json",
      "description": "Contém dados dos componentes da remuneração mensal dos servidores do poder Executivo do Estado de Minas Gerais",
      "title": "Remuneração de Junho de 2020",
      "mediatype": "text/csv",
      "encoding": "windows-1252",
      "dialect": "dialect.json",
      "format": "csv",
      "id": "6573337b-7ff5-4b1f-bfca-e3f30441996a",
      "hash": "sha256:5f98030a59e2bb83db57663098ad09a891dd90c44d38309a183c9d5287fbd6e8"
    },
    {
      "name": "servidores-2020-07",
      "path": "data/servidores-2020-07.csv.gz",
      "profile": "tabular-data-resource",
      "schema": "schema.json",
      "description": "Contém dados dos componentes da remuneração mensal dos servidores do poder Executivo do Estado de Minas Gerais",
      "title": "Remuneração de Julho de 2020",
      "mediatype": "text/csv",
      "encoding": "windows-1252",
      "dialect": "dialect.json",
      "format": "csv",
      "id": "94cf4201-136c-4ab8-bd16-a865d50cc4ca",
      "hash": "sha256:c5da68f376173628ebaaa709b4ad5784537aa63d6f00957c0ade0531e6b6f0b7"
    },
    {
      "name": "servidores-2020-08",
      "path": "data/servidores-2020-08.csv.gz",
      "profile": "tabular-data-resource",
      "schema": "schema.json",
      "description": "Contém dados dos componentes da remuneração mensal dos servidores do poder Executivo do Estado de Minas Gerais",
      "title": "Remuneração de Agosto de 2020",
      "mediatype": "text/csv",
      "encoding": "windows-1252",
      "dialect": "dialect.json",
      "format": "csv",
      "id": "3fb78517-4da1-4ad6-91bc-199da3a93cf9",
      "hash": "sha256:94a76af9d35d0eb0bfb26bd70cc8f0c82ab4e0717182a082ddb4122303db7a85"
    },
    {
      "name": "servidores-2020-09",
      "path": "data/servidores-2020-09.csv.gz",
      "profile": "tabular-data-resource",
      "schema": "schema.json",
      "description": "Contém dados dos componentes da remuneração mensal dos servidores do poder Executivo do Estado de Minas Gerais",
      "title": "Remuneração de Setembro de 2020",
      "mediatype": "text/csv",
      "encoding": "windows-1252",
      "dialect": "dialect.json",
      "format": "csv",
      "id": "d4d8be9a-5b5a-45db-aff2-d42ecbd0b07e",
      "hash": "sha256:ad374b6083e26b3ac31050688079c6ae422946dd38d89679746bfc5bd71dc3d6"
    },
    {
      "name": "servidores-2020-10",
      "path": "data/servidores-2020-10.csv.gz",
      "profile": "tabular-data-resource",
      "schema": "schema.json",
      "description": "Contém dados dos componentes da remuneração mensal dos servidores do poder Executivo do Estado de Minas Gerais",
      "title": "Remuneração de Outubro de 2020",
      "mediatype": "text/csv",
      "encoding": "windows-1252",
      "dialect": "dialect.json",
      "format": "csv",
      "id": "f1c3af25-44e0-4fe7-ae7c-79dad6d8903e",
      "hash": "sha256:5067d0f68a1baf11fafa6aee3af877653eb13c6b911e68e1954e8343270380bc"
    },
    {
      "name": "servidores-2020-11",
      "path": "data/servidores-2020-11.csv.gz",
      "profile": "tabular-data-resource",
      "schema": "schema.json",
      "description": "Contém dados dos componentes da remuneração mensal dos servidores do poder Executivo do Estado de Minas Gerais",
      "title": "Remuneração de Novembro de 2020",
      "mediatype": "text/csv",
      "encoding": "windows-1252",
      "dialect": "dialect.json",
      "format": "csv",
      "id": "c048fb04-aa68-49c3-b823-ed2f593b5923",
      "hash": "sha256:022849e8be514d37918214e0c3dfd52b6f20a3d1c502ac33bf77cb7199e96f43"
    },
    {
      "name": "servidores-2020-12",
      "path": "data/servidores-2020-12.csv.gz",
      "profile": "tabular-data-resource",
      "schema": "schema.json",
      "description": "Contém dados dos componentes da remuneração mensal dos servidores do poder Executivo do Estado de Minas Gerais",
      "title": "Remuneração de Dezembro de 2020",
      "mediatype": "text/csv",
      "encoding": "windows-1252",
      "dialect": "dialect.json",
      "format": "csv",
      "id": "54a366b2-ad3f-4180-92c6-68eecfbd801b",
      "hash": "sha256:7809038c17d36381177e49c4e0f4944397fa01e624dc419c05da2fe5d32e6b5b"
    },
    {
      "name": "servidores-2021-01",
      "path": "data/servidores-2021-01.csv.gz",
      "profile": "tabular-data-resource",
      "schema": "schema.json",
      "description": "Contém dados dos componentes da remuneração mensal dos servidores do poder Executivo do Estado de Minas Gerais",
      "title": "Remuneração de Janeiro de 2021",
      "mediatype": "text/csv",
      "encoding": "windows-1252",
      "dialect": "dialect.json",
      "format": "csv",
      "sources": [
        {
          "title": "Remuneração PMMG",
          "name": "servidores-2021-01-pmmg",
          "path": "https://drive.google.com/file/d/1OBHrCMJw_h4ZivwiIFZOxuz-oLbDbKEZ",
          "hash": "40e74d5c241d2d60c0db7037b9140d02"
        },
        {
          "title": "Remuneração CBMMG",
          "name": "servidores-2021-01-cbmmg",
          "path": "https://drive.google.com/file/d/1Lt7PdKMESj_KBW1245wuy_Py-35Ge-kF",
          "hash": "62482ab6138a13204671ca0f0d9dc657"
        },
        {
          "title": "Remuneração Civis",
          "name": "servidores-2021-01-civis",
          "path": "https://drive.google.com/file/d/1txNCuuQQMXnc95d4Nt9tKIkgrL1t9Y33",
          "hash": "39bf88e254d82d05e7dee4c1214914ec"
        }
      ],
      "id": "4f335998-3815-4d3a-a231-37adc3a7d46b",
      "hash": "sha256:a96f39bebc038ad315281c2c27d7611fb694295a70448b0b292c5161bb6cac6e"
    },
    {
      "name": "servidores-2021-02",
      "path": "data/servidores-2021-02.csv.gz",
      "profile": "tabular-data-resource",
      "schema": "schema.json",
      "description": "Contém dados dos componentes da remuneração mensal dos servidores do poder Executivo do Estado de Minas Gerais",
      "title": "Remuneração de Fevereiro de 2021",
      "mediatype": "text/csv",
      "encoding": "windows-1252",
      "dialect": "dialect.json",
      "format": "csv",
      "sources": [
        {
          "title": "Remuneração PMMG",
          "name": "servidores-2021-02-pmmg",
          "path": "https://drive.google.com/file/d/1O3j43IGKhcjfJmW8GzOQS9Q1Sx0xYBrz",
          "hash": "0a4ba21a12ed95b2b409e118d395b3e3"
        },
        {
          "title": "Remuneração CBMMG",
          "name": "servidores-2021-02-cbmmg",
          "path": "https://drive.google.com/file/d/1yjO-rFwg51B_TvCznByO4GcBNv-TcZYt",
          "hash": "24f1722b9af07a14cdee1ced702415ca"
        },
        {
          "title": "Remuneração Civis",
          "name": "servidores-2021-02-civis",
          "path": "https://drive.google.com/file/d/1J63GwXTDblBOu7hpG6rxeJ5Bj2Sh6-0w",
          "hash": "5ca9247270358a563551ed3de05cabaa"
        }
      ],
      "hash": "sha256:553718f4b35322b284d8b6ea139c070d1f81fa2f8d80b508f70b9591e67954ca",
      "id": "4c2bea49-5911-495a-935b-554615ff7099"
    },
    {
      "name": "servidores-2021-03",
      "path": "data/servidores-2021-03.csv.gz",
      "profile": "tabular-data-resource",
      "schema": "schema.json",
      "description": "Contém dados dos componentes da remuneração mensal dos servidores do poder Executivo do Estado de Minas Gerais",
      "title": "Remuneração de Março de 2021",
      "mediatype": "text/csv",
      "encoding": "windows-1252",
      "dialect": "dialect.json",
      "format": "csv",
      "sources": [
        {
          "title": "Remuneração PMMG",
          "name": "servidores-2021-03-pmmg",
          "path": "https://drive.google.com/file/d/1qVisX7RKVuxC8G_vxT8Fqk7Na70PU5RN",
          "hash": "07d68553c7f5a83a7bff216212b0edcf"
        },
        {
          "title": "Remuneração CBMMG",
          "name": "servidores-2021-03-cbmmg",
          "path": "https://drive.google.com/file/d/1dFcmOK4lb8m9Ysm-aiY0Ep8ZjcbrD2hL",
          "hash": "a46bb7947380cf7e2a59ed434dacd6d7"
        },
        {
          "title": "Remuneração Civis",
          "name": "servidores-2021-03-civis",
          "path": "https://drive.google.com/file/d/1gIQdB7tS9Xxsbqs8sDAC7vdvn0rJDeHy",
          "hash": "054e0f58d918f3381fbb8fc7f4b18a5a"
        }
      ],
      "hash": "sha256:3738de1c7b9792923544dd62a0cc5f9ff691dc527459a045bf682efb0510d122",
      "id": "36997a1d-b454-4d35-a689-0b45a7fe231e"
    },
    {
      "name": "servidores-2021-04",
      "path": "data/servidores-2021-04.csv.gz",
      "hash": "sha256:881e391d7b44262a051f3cb63708095c99772ba27175bcb66c14ea63e837c2d8",
      "profile": "tabular-data-resource",
      "schema": "schema.json",
      "description": "Contém dados dos componentes da remuneração mensal dos servidores do poder Executivo do Estado de Minas Gerais",
      "title": "Remuneração de Abril de 2021",
      "mediatype": "text/csv",
      "encoding": "windows-1252",
      "dialect": "dialect.json",
      "format": "csv",
      "sources": [
        {
          "title": "Remuneração PMMG",
          "name": "servidores-2021-04-pmmg",
          "path": "https://drive.google.com/file/d/1E36YgvUSd5xcig8l87_xMZgE_z13ZdgA",
          "hash": "00790904fce1bb3c98e6f3eeb2920fc9"
        },
        {
          "title": "Remuneração CBMMG",
          "name": "servidores-2021-04-cbmmg",
          "path": "https://drive.google.com/file/d/1InGAJkpZagLG9d-dcFHpVemycO_xaBDF",
          "hash": "eb8605dd5f8e15ee997b1f876f3b6691"
        },
        {
          "title": "Remuneração Civis",
          "name": "servidores-2021-04-civis",
          "path": "https://drive.google.com/file/d/1udyRGx7lQk8rsEz1_UP_ReQTnH02dSNR",
          "hash": "8181a3afe6ce08a5fa5028b4ee897af6"
        }
      ],
      "id": "7b9f90bf-eff7-410b-901e-b3e89b9b113b"
    },
    {
      "name": "servidores-2021-05",
      "path": "data/servidores-2021-05.csv.gz",
      "hash": "sha256:f4db11b4f0dcad365a186ce19c34dcef18c0a7276dc8a5c72e5a41d9a93fadb2",
      "profile": "tabular-data-resource",
      "schema": "schema.json",
      "description": "Contém dados dos componentes da remuneração mensal dos servidores do poder Executivo do Estado de Minas Gerais",
      "title": "Remuneração de Maio de 2021",
      "mediatype": "text/csv",
      "encoding": "windows-1252",
      "dialect": "dialect.json",
      "format": "csv",
      "sources": [
        {
          "title": "Remuneração PMMG",
          "name": "servidores-2021-05-pmmg",
          "path": "https://drive.google.com/file/d/1fEXNqDlsCHcHFdiyA2mr0Y3P3SCTNln5",
          "hash": "c16e6974e4c4f45e3e476067f9193266"
        },
        {
          "title": "Remuneração CBMMG",
          "name": "servidores-2021-05-cbmmg",
          "path": "https://drive.google.com/file/d/1PPGgVXmAvb6aj0zm0SctIR_I8Fe7UHld",
          "hash": "a2c2263ac91196ebd72c8ca294e2f9a0"
        },
        {
          "title": "Remuneração Civis",
          "name": "servidores-2021-05-civis",
          "path": "https://drive.google.com/file/d/18puPqKP1jQM4jRjVTvC_QEPZ2rX3qeDa",
          "hash": "6dfb3b8595eff3e7213b7e2a2f9c0675"
        }
      ],
      "id": "f0bf0707-7e22-4fcc-979c-1be729485f5e"
    },
    {
      "name": "servidores-2021-06",
      "path": "data/servidores-2021-06.csv.gz",
      "hash": "sha256:b88bd901bcdff96468cf1675444ce31e18a71cc4294545af0787edcd2e5f0e58",
      "profile": "tabular-data-resource",
      "schema": "schema.json",
      "description": "Contém dados dos componentes da remuneração mensal dos servidores do poder Executivo do Estado de Minas Gerais",
      "title": "Remuneração de Junho de 2021",
      "mediatype": "text/csv",
      "encoding": "windows-1252",
      "dialect": "dialect.json",
      "format": "csv",
      "sources": [
        {
          "title": "Remuneração PMMG",
          "name": "servidores-2021-06-pmmg",
          "path": "https://drive.google.com/file/d/1fVbnRdIS3S32De9JBELgphCv3qZ3Mqvs",
          "hash": "84d2cf290a36eb3ac8565b62a861f1e4"
        },
        {
          "title": "Remuneração CBMMG",
          "name": "servidores-2021-06-cbmmg",
          "path": "https://drive.google.com/file/d/18bmTYmRZIwqNztGRDKDInH-6Gdw42oR6",
          "hash": "4858c6b73852fa950c90b8901578296b"
        },
        {
          "title": "Remuneração Civis",
          "name": "servidores-2021-06-civis",
          "path": "https://drive.google.com/file/d/19flUkDz-O6Rr4VBDMGC71LrDC7wwZA3d",
          "hash": "b9ee2da3ea0d92833d8368f72788cf07"
        }
      ],
      "id": "dfc721f7-579f-47c2-8e72-97e8a0b3992d"
    },
        {
      "name": "servidores-2021-07",
      "path": "data/servidores-2021-07.csv.gz",
      "hash": "sha256:972a81e1b1fcb1d839cb2dc071de33736d859e712e0bd934ff8c2f138c1908e1",
      "profile": "tabular-data-resource",
      "schema": "schema.json",
      "description": "Contém dados dos componentes da remuneração mensal dos servidores do poder Executivo do Estado de Minas Gerais",
      "title": "Remuneração de Julho de 2021",
      "mediatype": "text/csv",
      "encoding": "windows-1252",
      "dialect": "dialect.json",
      "format": "csv",
      "sources": [
        {
          "title": "Remuneração PMMG",
          "name": "servidores-2021-07-pmmg",
          "path": "https://drive.google.com/file/d/1gsWGuez4bwDQ-GdiqARmuE7PE1jZE6ow",
          "hash": "040a3e5de85ed1334f6b501420c9f336"
        },
        {
          "title": "Remuneração CBMMG",
          "name": "servidores-2021-07-cbmmg",
          "path": "https://drive.google.com/file/d/1mUHjq1L-bx6nX7U-ccbHufFVYb4bpuV1",
          "hash": "522d3ce1c0d2d49d4d2818b9cdd673b6"
        },
        {
          "title": "Remuneração Civis",
          "name": "servidores-2021-07-civis",
          "path": "https://drive.google.com/file/d/1GZVv8RIdKEHxyiXUD8b4DFazsrpv_NWV",
          "hash": "8c91fe91a2c98224cac23cc93387d2df"
        }
      ],
      "id": "309a4211-a536-4e2f-9812-21ef70dd3d9e"
    },
    {
      "name": "servidores-2021-08",
      "path": "data/servidores-2021-08.csv.gz",
      "hash": "sha256:1399b5559197980c44695c39102469d3ebb21f8a9bdd8c10c7fe96433e57e85f",
      "profile": "tabular-data-resource",
      "schema": "schema.json",
      "description": "Contém dados dos componentes da remuneração mensal dos servidores do poder Executivo do Estado de Minas Gerais",
      "title": "Remuneração de Agosto de 2021",
      "mediatype": "text/csv",
      "encoding": "windows-1252",
      "dialect": "dialect.json",
      "format": "csv",
      "sources": [
        {
          "title": "Remuneração PMMG",
          "name": "servidores-2021-08-pmmg",
          "path": "https://drive.google.com/file/d/14YvtysUBhatKxEvsF8oN4pgF1a2VTT6T",
          "hash": "a4ff06af9485c5d13900f5179ac5573d"
        },
        {
          "title": "Remuneração CBMMG",
          "name": "servidores-2021-08-cbmmg",
          "path": "https://drive.google.com/file/d/1sKdilM1GMWfyy15AmgWOetf5kGYHX9mG",
          "hash": "a6b34889e6c83b30fb1e41636e4a3e9b"
        },
        {
          "title": "Remuneração Civis",
          "name": "servidores-2021-08-civis",
          "path": "https://drive.google.com/file/d/1YEcp5YjoHtTaQNKVLdNrl80E-cnhjBFC",
          "hash": "ad69a8836f5fbf0367ce5fa0cb70a47d"
        }
      ],
      "id": "75bd5a6b-f6cd-4b7a-89e6-49ad67f959bb"
    },
    {
      "name": "servidores-2021-09",
      "path": "data/servidores-2021-09.csv.gz",
      "hash": "sha256:3625e1685e1d9ec38ac0648a9954a82432832fd252f7d56c478cd8876545eab0",
      "profile": "tabular-data-resource",
      "schema": "schema.json",
      "description": "Contém dados dos componentes da remuneração mensal dos servidores do poder Executivo do Estado de Minas Gerais",
      "title": "Remuneração de Setembro de 2021",
      "mediatype": "text/csv",
      "encoding": "windows-1252",
      "dialect": "dialect.json",
      "format": "csv",
      "sources": [
        {
          "title": "Remuneração PMMG",
          "name": "servidores-2021-09-pmmg",
          "path": "https://drive.google.com/file/d/1QUeFoMRuSQ7YixUXsBIV9RWPdeGbXJIq",
          "hash": "b2085d118a03086dde8b0b4228b3d0ad"
        },
        {
          "title": "Remuneração CBMMG",
          "name": "servidores-2021-09-cbmmg",
          "path": "https://drive.google.com/file/d/14qf9SUOjZcMdqKfj33p7jMJDVWJsa-ZM",
          "hash": "371b23767219273b0676ce103ec7c369"
        },
        {
          "title": "Remuneração Civis",
          "name": "servidores-2021-09-civis",
          "path": "https://drive.google.com/file/d/1eJFW5AojvghALNnEfyLu35llT7NwWf1x",
          "hash": "7fe698e48b4906914237e8594e8de396"
        }
      ],
      "id": "b8ee5330-305a-447e-aa37-f47806e22649"
    },
    {
      "name": "servidores-2021-10",
      "path": "data/servidores-2021-10.csv.gz",
      "hash": "sha256:4be467d52a340139806262cc278beece494b27f318b49e788d515fe354719ab1",
      "profile": "tabular-data-resource",
      "schema": "schema.json",
      "description": "Contém dados dos componentes da remuneração mensal dos servidores do poder Executivo do Estado de Minas Gerais",
      "title": "Remuneração de Outubro de 2021",
      "mediatype": "text/csv",
      "encoding": "windows-1252",
      "dialect": "dialect.json",
      "format": "csv",
      "sources": [
        {
          "title": "Remuneração PMMG",
          "name": "servidores-2021-10-pmmg",
          "path": "https://drive.google.com/file/d/1zO22Vya8HmuO3q-2ceAo-Ryxx5JvQ2aH",
          "hash": "b95e4a827eae85e1088c8522bb6c457d"
        },
        {
          "title": "Remuneração CBMMG",
          "name": "servidores-2021-10-cbmmg",
          "path": "https://drive.google.com/file/d/1oYoWJavb4ZYpFjWLOWo4XvNgEib-dVct",
          "hash": "e0f9c383fff3b55018db27986e3d122f"
        },
        {
          "title": "Remuneração Civis",
          "name": "servidores-2021-10-civis",
          "path": "https://drive.google.com/file/d/1uu_MmOnHh8Cx210SUkmt2R5u7wsFs3VK",
          "hash": "59c9bc9590839ddd70f7c527ec2007d2"
        }
      ],
      "id": "adee91df-d0c4-4b8c-8c86-4328e95669c0"
    },
    {
      "name": "servidores-2021-11",
      "path": "data/servidores-2021-11.csv.gz",
      "hash": "sha256:d8c0e8e17b35fcf6ba9395488f4bf2d884987d6740506a158f69fbb7d5041560",
      "profile": "tabular-data-resource",
      "schema": "schema.json",
      "description": "Contém dados dos componentes da remuneração mensal dos servidores do poder Executivo do Estado de Minas Gerais",
      "title": "Remuneração de Novembro de 2021",
      "mediatype": "text/csv",
      "encoding": "windows-1252",
      "dialect": "dialect.json",
      "format": "csv",
      "sources": [
        {
          "title": "Remuneração PMMG",
          "name": "servidores-2021-11-pmmg",
          "path": "https://drive.google.com/file/d/1YjE1oxyRYHO-YEZUkjh8SfvxJ0tPDYy4",
          "hash": "7c17a7b4f58d5c19fe55a18689dd598b"
        },
        {
          "title": "Remuneração CBMMG",
          "name": "servidores-2021-11-cbmmg",
          "path": "https://drive.google.com/file/d/1oTL3ObgC0qeMLp8nYLI3F3TjFc_XFquK",
          "hash": "96ac06a1a1393dc0ca747d9db8d59d64"
        },
        {
          "title": "Remuneração Civis",
          "name": "servidores-2021-11-civis",
          "path": "https://drive.google.com/file/d/1g2Q6T56r4YCWs36Bljw7r4u59gUexdwU",
          "hash": "b74f6e8f323472f7ba06592c9ef60ccc"
        }
      ],
      "id": "999eb55f-df3b-4e7d-a3a5-43ebdc14aca3"
    },
    {
      "name": "servidores-2021-12",
      "path": "data/servidores-2021-12.csv.gz",
      "hash": "sha256:87c35d5f71f1772d1b5923e3194fdd07facdc51cd18b0a38712a6f65781c1c0a",
      "profile": "tabular-data-resource",
      "schema": "schema.json",
      "description": "Contém dados dos componentes da remuneração mensal dos servidores do poder Executivo do Estado de Minas Gerais",
      "title": "Remuneração de Dezembro de 2021",
      "mediatype": "text/csv",
      "encoding": "windows-1252",
      "dialect": "dialect.json",
      "format": "csv",
      "sources": [
        {
          "title": "Remuneração PMMG",
          "name": "servidores-2021-12-pmmg",
          "path": "https://drive.google.com/file/d/1_MkQIRrKol_JQmuaRq9JrNlflhCo6KDz",
          "hash": "efb051258854c94b5dd7793801629f0c"
        },
        {
          "title": "Remuneração CBMMG",
          "name": "servidores-2021-12-cbmmg",
          "path": "https://drive.google.com/file/d/13bOAUGc3kr-vOMu0s96GsmK4KpM9uUub",
          "hash": "7bdff068c3555a977756382ea34fc5dc"
        },
        {
          "title": "Remuneração Civis",
          "name": "servidores-2021-12-civis",
          "path": "https://drive.google.com/file/d/1DKcTCT67rw0oW4_n8UQTAgOSYO1XQdKI",
          "hash": "e05d49ce56aac0da01e222b24ac92969"
        }
      ],
      "id": "89d95c5e-5572-47b1-ba6b-601b6aa30593"
    },
    {
      "name": "servidores-2022-01",
      "path": "data/servidores-2022-01.csv.gz",
      "hash": "sha256:5fbbdffdc97378c80df8deb17be7d123440f882f2d8b9ba25a9db08fabb4805d",
      "profile": "tabular-data-resource",
      "schema": "schema.json",
      "description": "Contém dados dos componentes da remuneração mensal dos servidores do poder Executivo do Estado de Minas Gerais",
      "title": "Remuneração de Janeiro de 2022",
      "mediatype": "text/csv",
      "encoding": "windows-1252",
      "dialect": "dialect.json",
      "format": "csv",
      "sources": [
        {
          "title": "Remuneração PMMG",
          "name": "servidores-2022-01-pmmg",
          "path": "https://drive.google.com/file/d/1asqDYUom0skml7aJofgnzFGDeK1oz7ha",
          "hash": "eb9f748187f1d9c5fd95e7810b5ef88c"
        },
        {
          "title": "Remuneração CBMMG",
          "name": "servidores-2022-01-cbmmg",
          "path": "https://drive.google.com/file/d/1CmdG40moKaGsI4tPNqjGbzNmoBU-Ynoc",
          "hash": "9a17a0a8ce5047788a8a51a2bcbd7a68"
        },
        {
          "title": "Remuneração Civis",
          "name": "servidores-2022-01-civis",
          "path": "https://drive.google.com/file/d/1pZG5hJJzs0_cOyWVTgZ_Q5tNi4fI1zXi",
          "hash": "333d472bf35daf6d832436987ecc34a6"
        }
      ],
      "id": "d2e68594-6de9-4614-b2bc-349ca1890538"
    },
        {
      "name": "servidores-2022-02",
      "path": "data/servidores-2022-02.csv.gz",
      "hash": "sha256:7e8d4724dc3f93c1918135f82dc56aa5dfd061ef002fbfb5d334e1adcfa273dd",
      "profile": "tabular-data-resource",
      "schema": "schema.json",
      "description": "Contém dados dos componentes da remuneração mensal dos servidores do poder Executivo do Estado de Minas Gerais",
      "title": "Remuneração de Fevereiro de 2022",
      "mediatype": "text/csv",
      "encoding": "windows-1252",
      "dialect": "dialect.json",
      "format": "csv",
      "sources": [
        {
          "title": "Remuneração PMMG",
          "name": "servidores-2022-02-pmmg",
          "path": "https://drive.google.com/file/d/1G7_vrs3KP5-7uA25GorDcUV2w1J0wlOx",
          "hash": "8cd1fdc2b8514036a80eb2dfa95d6feb"
        },
        {
          "title": "Remuneração CBMMG",
          "name": "servidores-2022-02-cbmmg",
          "path": "https://drive.google.com/file/d/14qzS7fLKFthiXlN9TNVKrPip1E2OzFqG",
          "hash": "62e62278b09cee32573fea473a956ac6"
        },
        {
          "title": "Remuneração Civis",
          "name": "servidores-2022-02-civis",
          "path": "https://drive.google.com/file/d/10xMtTOd2f9EZvIsvQuoFrVV3iScvs336",
          "hash": "e589a34f6b263da63904a05faa5ee750"
        }
      ],
      "id": "0f838f07-e183-43fa-a36f-efc096c84951"
    },
    {
      "name": "servidores-2022-03",
      "path": "data/servidores-2022-03.csv.gz",
      "hash": "sha256:75eeee7362300c5592c75c96f6f1acae800287f35926fe977f2cbb0c17c679b2",
      "profile": "tabular-data-resource",
      "schema": "schema.json",
      "description": "Contém dados dos componentes da remuneração mensal dos servidores do poder Executivo do Estado de Minas Gerais",
      "title": "Remuneração de Março de 2022",
      "mediatype": "text/csv",
      "encoding": "windows-1252",
      "dialect": "dialect.json",
      "format": "csv",
      "sources": [
        {
          "title": "Remuneração PMMG",
          "name": "servidores-2022-03-pmmg",
          "path": "https://drive.google.com/file/d/1AqCsyfV5UzEDF_BhftTde7AGnb1uB5tX",
          "hash": "fd3e3b873532496970de3bb0ef9de48e"
        },
        {
          "title": "Remuneração CBMMG",
          "name": "servidores-2022-03-cbmmg",
          "path": "https://drive.google.com/file/d/1b-tCY1i8LAlKsc91IZoDlWdetS7Q1vFh",
          "hash": "1673e77ed50ea7a578c004c2876d7132"
        },
        {
          "title": "Remuneração Civis",
          "name": "servidores-2022-03-civis",
          "path": "https://drive.google.com/file/d/1X33umvC9TOIfbH5-pdK5C6yZJk-H91Xb",
          "hash": "55cadccb1356110523cf6045abef3650"
        }
      ],
      "id": "811cec3e-c6b0-479a-ab31-c714e5a1c5a2"
    },
        {
      "name": "servidores-2022-04",
      "path": "data/servidores-2022-04.csv.gz",
      "hash": "sha256:2a45b8e05625e4e03153a4e309d327943b62fd8fc26e2f79b7343884f73e8f7d",
      "profile": "tabular-data-resource",
      "schema": "schema.json",
      "description": "Contém dados dos componentes da remuneração mensal dos servidores do poder Executivo do Estado de Minas Gerais",
      "title": "Remuneração de Abril de 2022",
      "mediatype": "text/csv",
      "encoding": "windows-1252",
      "dialect": "dialect.json",
      "format": "csv",
      "sources": [
        {
          "title": "Remuneração PMMG",
          "name": "servidores-2022-04-pmmg",
          "path": "https://drive.google.com/file/d/1IDZu2Fv5Hjmyg0PTU2oaiAJR2xJki7aE",
          "hash": "97c81a68a5935d80d6a1fc6b1a3c7998"
        },
        {
          "title": "Remuneração CBMMG",
          "name": "servidores-2022-04-cbmmg",
          "path": "https://drive.google.com/file/d/1lja9iw6IiseTPpP4mz7VLrMOORIGXx1Z",
          "hash": "b1495333789a369a4b43c78dd9ac9a3b"
        },
        {
          "title": "Remuneração Civis",
          "name": "servidores-2022-04-civis",
          "path": "https://drive.google.com/file/d/1Fa5lGYjPqog-EiVo85_t734cRH8liEL5",
          "hash": "6a91dec2faa7288ef6d5f8543a249aab"
        }
      ]
    },
        {
      "name": "servidores-2022-05",
      "path": "data/servidores-2022-05.csv.gz",
      "hash": "sha256:627bda736c3d43189e8cf26aea1788507d4551d922ae2ae7c01001c5084c3e07",
      "profile": "tabular-data-resource",
      "schema": "schema.json",
      "description": "Contém dados dos componentes da remuneração mensal dos servidores do poder Executivo do Estado de Minas Gerais",
      "title": "Remuneração de Maio de 2022",
      "mediatype": "text/csv",
      "encoding": "windows-1252",
      "dialect": "dialect.json",
      "format": "csv",
      "sources": [
        {
          "title": "Remuneração PMMG",
          "name": "servidores-2022-05-pmmg",
          "path": "https://drive.google.com/file/d/1n7Uq2Kh0aL2x63fx2WhmXukLkKSHe6SH",
          "hash": "14460a5a395f23f40be03412a0252360"
        },
        {
          "title": "Remuneração CBMMG",
          "name": "servidores-2022-05-cbmmg",
          "path": "https://drive.google.com/file/d/1V2jtAmCvHTmkgE981h8osIXadCspb5oR",
          "hash": "86802c986ac2798b4be577797ea73b0f"
        },
        {
          "title": "Remuneração Civis",
          "name": "servidores-2022-05-civis",
          "path": "https://drive.google.com/file/d/1BsgPrBFkaiy_MVCXIuJnVx1xUmKI7cdM",
          "hash": "53843d7e808cd2fe37627ebd8af53941"
        }
      ]
    },
        {
      "name": "servidores-2022-06",
      "path": "data/servidores-2022-06.csv.gz",
      "hash": "sha256:8de02ee8ffc12f86a64f8ff12dcd0e7d3e5baa931f302a08f6972b4b087a9789",
      "profile": "tabular-data-resource",
      "schema": "schema.json",
      "description": "Contém dados dos componentes da remuneração mensal dos servidores do poder Executivo do Estado de Minas Gerais",
      "title": "Remuneração de Junho de 2022",
      "mediatype": "text/csv",
      "encoding": "windows-1252",
      "dialect": "dialect.json",
      "format": "csv",
      "sources": [
        {
          "title": "Remuneração PMMG",
          "name": "servidores-2022-06-pmmg",
          "path": "https://drive.google.com/file/d/1-hqwz7lKxPem1gOWJvt7NbX6o5YxHyoG",
          "hash": "c342f97e8c696c0e8c0c222f596261ba"
        },
        {
          "title": "Remuneração CBMMG",
          "name": "servidores-2022-06-cbmmg",
          "path": "https://drive.google.com/file/d/1YFcTMobiLx2YuNKd3J55Mv08zAbcY3u9",
          "hash": "612673b72244556285d527771d4070c2"
        },
        {
          "title": "Remuneração Civis",
          "name": "servidores-2022-06-civis",
          "path": "https://drive.google.com/file/d/1alPJqz6iqg9EdkZqOsFbLmlNVG7QrGTf",
          "hash": "0400223ab8ac672aa76985f49cd5f0e8"
        }
      ]
    },
        {
      "name": "servidores-2022-07",
      "path": "data/servidores-2022-07.csv.gz",
      "hash": "sha256:58dd83d03526fac5c7c3d216c6a071980cba4b32e5ea6742e12421c5992120ad",
      "profile": "tabular-data-resource",
      "schema": "schema.json",
      "description": "Contém dados dos componentes da remuneração mensal dos servidores do poder Executivo do Estado de Minas Gerais",
      "title": "Remuneração de Julho de 2022",
      "mediatype": "text/csv",
      "encoding": "windows-1252",
      "dialect": "dialect.json",
      "format": "csv",
      "sources": [
        {
          "title": "Remuneração PMMG",
          "name": "servidores-2022-07-pmmg",
          "path": "https://drive.google.com/file/d/1pqce6MlBUR6j47Lxk2HYpt86yQOZj9LP",
          "hash": "6993bf3f918cfcd5f0974412ddf6b536"
        },
        {
          "title": "Remuneração CBMMG",
          "name": "servidores-2022-07-cbmmg",
          "path": "https://drive.google.com/file/d/1Qk2AcveP63bVgLOEB86RiIFIWHR6rqax",
          "hash": "be069cfa0482c7164d7b4f46a06efa58"
        },
        {
          "title": "Remuneração Civis",
          "name": "servidores-2022-07-civis",
          "path": "https://drive.google.com/file/d/1eECHIYV9nSgp2s9FOR2EnXhr9yLWpCq5",
          "hash": "5a7074c400b23979845c4db735027a79"
        }
      ]
    },
        {
      "name": "servidores-2022-08",
      "path": "data/servidores-2022-08.csv.gz",
      "hash": "sha256:40a5f1c0a124ff4e830065c83f405be5e0975d58db0ceac85373ca902f7ef2d2",
      "profile": "tabular-data-resource",
      "schema": "schema.json",
      "description": "Contém dados dos componentes da remuneração mensal dos servidores do poder Executivo do Estado de Minas Gerais",
      "title": "Remuneração de Agosto de 2022",
      "mediatype": "text/csv",
      "encoding": "windows-1252",
      "dialect": "dialect.json",
      "format": "csv",
      "sources": [
        {
          "title": "Remuneração PMMG",
          "name": "servidores-2022-08-pmmg",
          "path": "https://drive.google.com/file/d/1JjQ4_1YFET6fChCZvFm3wMUM1o--7yXx",
          "hash": "2262b03cb969e3f21443db6d25f2363c"
        },
        {
          "title": "Remuneração CBMMG",
          "name": "servidores-2022-08-cbmmg",
          "path": "https://drive.google.com/file/d/1eCJxif5rq_840xUnwpH80kecY6_x9eBB",
          "hash": "9b81e8c899795e701544233f1a60f485"
        },
        {
          "title": "Remuneração Civis",
          "name": "servidores-2022-08-civis",
          "path": "https://drive.google.com/file/d/1UCw8oyOiiJ73jvMaozrblm39SO49TGS8",
          "hash": "28308d55352cd114db6f02f2b04ac4ce"
        }
      ]
    }
  ],
  "keywords": [
    "salário",
    "remuneração",
    "Portal da Transparência"
  ],
  "name": "remuneracao-servidores-ativos",
  "owner_org": "controladoria-geral-do-estado-cge",
  "title": "Remuneração dos Servidores Ativos do Poder Executivo",
  "description": "Remuneração dos Servidores Ativos do Poder Executivo",
  "private": "false",
  "state": "active",
  "version": "0.1.0",
  "sources": [
    {
      "title": "Github",
      "path": "https://github.com/dados-mg/remuneracao"
    }
  ],
  "licenses": [
    {
      "name": "CC-BY-4.0",
      "title": "Creative Commons Attribution 4.0",
      "path": "https://creativecommons.org/licenses/by/4.0/"
    }
  ],
  "contributors": [
    {
      "title": "Controladoria-Geral do Estado",
      "role": "publisher",
      "organization": "controladoria-geral-do-estado-cge"
    },
    {
      "title": "Diretoria Central de Transparência Ativa",
      "path": "https://cge.mg.gov.br/a-cge/quem-e-quem/subcontroladoria-de-transparencia-e-integridade",
      "email": "transparencia@cge.mg.gov.br",
      "role": "maintainer"
    }
  ]
}
